{
    "a": [
        "det"
    ],
    "an": [
        "det"
    ],
    "the": [
        "det"
    ],
    "some": [
        "det"
    ],
    "i": [
        "pronoun"
    ],
    "you": [
        "pronoun"
    ],
    "he": [
        "pronoun"
    ],
    "she": [
        "pronoun"
    ],
    "it": [
        "pronoun"
    ],
    "we": [
        "pronoun"
    ],
    "they": [
        "pronoun"
    ],
    "this": [
        "pronoun"
    ],
    "that": [
        "pronoun",
        "that"
    ],
    "these": [
        "pronoun"
    ],
    "those": [
        "pronoun"
    ],
    "my": [
        "possessive_adjective"
    ],
    "your": [
        "possessive_adjective"
    ],
    "his": [
        "possessive_adjective",
        "possessive_pronoun"
    ],
    "her": [
        "possessive_adjective"
    ],
    "its": [
        "possessive_adjective",
        "possessive_pronoun"
    ],
    "our": [
        "possessive_adjective"
    ],
    "their": [
        "possessive_adjective"
    ],
    "mine": [
        "possessive_pronoun"
    ],
    "yours": [
        "possessive_pronoun"
    ],
    "hers": [
        "possessive_pronoun"
    ],
    "ours": [
        "possessive_pronoun"
    ],
    "theirs": [
        "possessive_pronoun"
    ],
    "London": [
        "proper_noun"
    ],
    "Paris": [
        "proper_noun"
    ],
    "Berlin": [
        "proper_noun"
    ],
    "Moscow": [
        "proper_noun"
    ],
    "Tokyo": [
        "proper_noun"
    ],
    "Beijing": [
        "proper_noun"
    ],
    "New York": [
        "proper_noun"
    ],
    "Los Angeles": [
        "proper_noun"
    ],
    "San Francisco": [
        "proper_noun"
    ],
    "Roxy": [
        "proper_noun"
    ],
    "Max": [
        "proper_noun"
    ],
    "Daisy": [
        "proper_noun"
    ],
    "Sue": [
        "proper_noun"
    ],
    "John": [
        "proper_noun"
    ],
    "Mary": [
        "proper_noun"
    ],
    "Peter": [
        "proper_noun"
    ],
    "Paul": [
        "proper_noun"
    ],
    "Carlos": [
        "proper_noun"
    ],
    "Jesus": [
        "proper_noun"
    ],
    "Darnell": [
        "proper_noun"
    ],
    "Milly": [
        "proper_noun"
    ],
    "Alice": [
        "proper_noun"
    ],
    "Anna": [
        "proper_noun"
    ],
    "Becky": [
        "proper_noun"
    ],
    "Bertha": [
        "proper_noun"
    ],
    "Bob": [
        "proper_noun"
    ],
    "Charlie": [
        "proper_noun"
    ],
    "Carol": [
        "proper_noun"
    ],
    "David": [
        "proper_noun"
    ],
    "Disney": [
        "proper_noun"
    ],
    "Emily": [
        "proper_noun"
    ],
    "Eve": [
        "proper_noun"
    ],
    "Frank": [
        "proper_noun"
    ],
    "Grace": [
        "proper_noun"
    ],
    "Gloria": [
        "proper_noun"
    ],
    "Henry": [
        "proper_noun"
    ],
    "water": [
        "uncountable_noun"
    ],
    "milk": [
        "uncountable_noun"
    ],
    "rice": [
        "uncountable_noun"
    ],
    "money": [
        "uncountable_noun"
    ],
    "food": [
        "uncountable_noun"
    ],
    "air": [
        "uncountable_noun"
    ],
    "light": [
        "uncountable_noun"
    ],
    "heat": [
        "uncountable_noun"
    ],
    "cold": [
        "uncountable_noun"
    ],
    "ice": [
        "uncountable_noun"
    ],
    "bread": [
        "uncountable_noun"
    ],
    "flour": [
        "uncountable_noun"
    ],
    "snow": [
        "uncountable_noun",
        "noun"
    ],
    "rain": [
        "uncountable_noun",
        "noun"
    ],
    "news": [
        "uncountable_noun"
    ],
    "information": [
        "uncountable_noun"
    ],
    "knowledge": [
        "uncountable_noun"
    ],
    "wisdom": [
        "uncountable_noun"
    ],
    "furniture": [
        "uncountable_noun"
    ],
    "equipment": [
        "uncountable_noun"
    ],
    "luggage": [
        "uncountable_noun"
    ],
    "time": [
        "uncountable_noun"
    ],
    "sand": [
        "uncountable_noun"
    ],
    "popcorn": [
        "uncountable_noun"
    ],
    "music": [
        "uncountable_noun",
        "noun"
    ],
    "soda": [
        "uncountable_noun"
    ],
    "pizza": [
        "uncountable_noun"
    ],
    "fish": [
        "uncountable_noun",
        "noun",
        "vb",
        "vbp"
    ],
    "meat": [
        "uncountable_noun",
        "noun"
    ],
    "chicken": [
        "uncountable_noun",
        "noun"
    ],
    "broccoli": [
        "uncountable_noun"
    ],
    "candy": [
        "uncountable_noun",
        "noun"
    ],
    "magic": [
        "uncountable_noun"
    ],
    "stuff": [
        "uncountable_noun",
        "noun"
    ],
    "yogurt": [
        "uncountable_noun",
        "noun"
    ],
    "honey": [
        "uncountable_noun",
        "noun"
    ],
    "smoke": [
        "uncountable_noun",
        "vb",
        "vbp"
    ],
    "cream": [
        "uncountable_noun",
        "noun"
    ],
    "cheese": [
        "uncountable_noun"
    ],
    "advice": [
        "uncountable_noun",
        "noun"
    ],
    "jewelry": [
        "uncountable_noun"
    ],
    "blood": [
        "uncountable_noun"
    ],
    "biology": [
        "uncountable_noun"
    ],
    "astronomy": [
        "uncountable_noun"
    ],
    "chemistry": [
        "uncountable_noun"
    ],
    "research": [
        "uncountable_noun"
    ],
    "football": [
        "uncountable_noun"
    ],
    "tennis": [
        "uncountable_noun"
    ],
    "baseball": [
        "uncountable_noun"
    ],
    "jenga": [
        "uncountable_noun"
    ],
    "soccer": [
        "uncountable_noun"
    ],
    "badminton": [
        "uncountable_noun"
    ],
    "not": [
        "not"
    ],
    "to": [
        "to",
        "goal_preposition",
        "preposition"
    ],
    "s": [
        "s"
    ],
    "if": [
        "interrogative_subordinator"
    ],
    "whether": [
        "interrogative_subordinator"
    ],
    "big": [
        "adj"
    ],
    "small": [
        "adj"
    ],
    "little": [
        "adj"
    ],
    "happy": [
        "adj",
        "adj_declarative_cl",
        "adj_to_inf_cl"
    ],
    "sad": [
        "adj",
        "adj_pp",
        "adj_declarative_cl",
        "adj_to_inf_cl"
    ],
    "icy": [
        "adj"
    ],
    "thoughtful": [
        "adj"
    ],
    "careful": [
        "adj"
    ],
    "lonely": [
        "adj"
    ],
    "kind": [
        "adj"
    ],
    "quick": [
        "adj"
    ],
    "interesting": [
        "adj"
    ],
    "mysterious": [
        "adj"
    ],
    "free": [
        "adj"
    ],
    "young": [
        "adj"
    ],
    "old": [
        "adj"
    ],
    "interested": [
        "adj_pp"
    ],
    "glad": [
        "adj_pp",
        "adj_declarative_cl",
        "adj_to_inf_cl"
    ],
    "sorry": [
        "adj_pp",
        "adj_declarative_cl",
        "adj_to_inf_cl"
    ],
    "quickly": [
        "adv"
    ],
    "slowly": [
        "adv"
    ],
    "happily": [
        "adv"
    ],
    "now": [
        "adv"
    ],
    "very": [
        "adv"
    ],
    "clearly": [
        "adv"
    ],
    "sadly": [
        "adv"
    ],
    "suddenly": [
        "adv"
    ],
    "even": [
        "precorenp_modifier"
    ],
    "all": [
        "precorenp_modifier"
    ],
    "too": [
        "postcorenp_modifier"
    ],
    "altogether": [
        "postcorenp_modifier"
    ],
    "can": [
        "modal"
    ],
    "could": [
        "modal"
    ],
    "may": [
        "modal"
    ],
    "might": [
        "modal"
    ],
    "shall": [
        "modal"
    ],
    "should": [
        "modal"
    ],
    "will": [
        "modal"
    ],
    "would": [
        "modal"
    ],
    "must": [
        "modal"
    ],
    "how": [
        "how"
    ],
    "why": [
        "why"
    ],
    "who": [
        "wh"
    ],
    "what": [
        "wh"
    ],
    "which": [
        "wh",
        "which"
    ],
    "where": [
        "wh"
    ],
    "when": [
        "wh"
    ],
    "is": [
        "is",
        "vbz",
        "vbz_ap",
        "vbz_vbg_cl",
        "vbz_np"
    ],
    "are": [
        "are",
        "vbp",
        "vbp_ap",
        "vbp_vbg_cl",
        "vbp_np"
    ],
    "were": [
        "were",
        "vbd",
        "vbd_ap",
        "vbd_vbg_cl",
        "vbd_np"
    ],
    "does": [
        "does"
    ],
    "do": [
        "do",
        "vb_bare_inf_cl",
        "vbp_bare_inf_cl",
        "vb_np",
        "vbp_np"
    ],
    "did": [
        "did"
    ],
    "apple": [
        "noun"
    ],
    "banana": [
        "noun"
    ],
    "car": [
        "noun"
    ],
    "house": [
        "noun"
    ],
    "tree": [
        "noun"
    ],
    "flower": [
        "noun"
    ],
    "daisy": [
        "noun"
    ],
    "bee": [
        "noun"
    ],
    "dog": [
        "noun"
    ],
    "cat": [
        "noun"
    ],
    "cow": [
        "noun"
    ],
    "pig": [
        "noun"
    ],
    "horse": [
        "noun"
    ],
    "sheep": [
        "noun"
    ],
    "bird": [
        "noun"
    ],
    "hummingbird": [
        "noun"
    ],
    "rhinoceros": [
        "noun"
    ],
    "elephant": [
        "noun"
    ],
    "whale": [
        "noun"
    ],
    "octopus": [
        "noun"
    ],
    "book": [
        "noun"
    ],
    "pen": [
        "noun"
    ],
    "pencil": [
        "noun"
    ],
    "computer": [
        "noun"
    ],
    "phone": [
        "noun"
    ],
    "television": [
        "noun"
    ],
    "radio": [
        "noun"
    ],
    "newspaper": [
        "noun"
    ],
    "magazine": [
        "noun"
    ],
    "letter": [
        "noun"
    ],
    "email": [
        "noun"
    ],
    "picture": [
        "noun"
    ],
    "photograph": [
        "noun"
    ],
    "video": [
        "noun"
    ],
    "movie": [
        "noun"
    ],
    "song": [
        "noun"
    ],
    "dance": [
        "noun",
        "vb",
        "vbp"
    ],
    "game": [
        "noun"
    ],
    "toy": [
        "noun"
    ],
    "snowman": [
        "noun"
    ],
    "ball": [
        "noun"
    ],
    "doll": [
        "noun"
    ],
    "carpet": [
        "noun"
    ],
    "floor": [
        "noun"
    ],
    "ceiling": [
        "noun"
    ],
    "wall": [
        "noun"
    ],
    "window": [
        "noun"
    ],
    "door": [
        "noun"
    ],
    "roof": [
        "noun"
    ],
    "stair": [
        "noun"
    ],
    "step": [
        "noun"
    ],
    "hall": [
        "noun"
    ],
    "room": [
        "noun"
    ],
    "kitchen": [
        "noun"
    ],
    "stove": [
        "noun"
    ],
    "spatula": [
        "noun"
    ],
    "spoon": [
        "noun"
    ],
    "knife": [
        "noun"
    ],
    "fork": [
        "noun"
    ],
    "bowl": [
        "noun"
    ],
    "plate": [
        "noun"
    ],
    "cup": [
        "noun"
    ],
    "glass": [
        "noun"
    ],
    "mug": [
        "noun"
    ],
    "platter": [
        "noun"
    ],
    "dish": [
        "noun"
    ],
    "vegetable": [
        "noun"
    ],
    "grain": [
        "noun"
    ],
    "bathroom": [
        "noun"
    ],
    "bedroom": [
        "noun"
    ],
    "bed": [
        "noun"
    ],
    "table": [
        "noun"
    ],
    "chair": [
        "noun"
    ],
    "sofa": [
        "noun"
    ],
    "couch": [
        "noun"
    ],
    "desk": [
        "noun"
    ],
    "shelf": [
        "noun"
    ],
    "drawer": [
        "noun"
    ],
    "cabinet": [
        "noun"
    ],
    "closet": [
        "noun"
    ],
    "mirror": [
        "noun"
    ],
    "sink": [
        "noun"
    ],
    "toilet": [
        "noun"
    ],
    "bathtub": [
        "noun"
    ],
    "shower": [
        "noun"
    ],
    "towel": [
        "noun"
    ],
    "soap": [
        "noun"
    ],
    "shampoo": [
        "noun"
    ],
    "toothbrush": [
        "noun"
    ],
    "toothpaste": [
        "noun"
    ],
    "hairbrush": [
        "noun"
    ],
    "lightbulb": [
        "noun"
    ],
    "lamp": [
        "noun"
    ],
    "candle": [
        "noun"
    ],
    "garden": [
        "noun"
    ],
    "yard": [
        "noun"
    ],
    "street": [
        "noun"
    ],
    "road": [
        "noun"
    ],
    "highway": [
        "noun"
    ],
    "bridge": [
        "noun"
    ],
    "tunnel": [
        "noun"
    ],
    "river": [
        "noun"
    ],
    "lake": [
        "noun"
    ],
    "ocean": [
        "noun"
    ],
    "sea": [
        "noun"
    ],
    "beach": [
        "noun"
    ],
    "mountain": [
        "noun"
    ],
    "hill": [
        "noun"
    ],
    "valley": [
        "noun"
    ],
    "forest": [
        "noun"
    ],
    "jungle": [
        "noun"
    ],
    "desert": [
        "noun"
    ],
    "island": [
        "noun"
    ],
    "continent": [
        "noun"
    ],
    "country": [
        "noun"
    ],
    "state": [
        "noun"
    ],
    "city": [
        "noun"
    ],
    "town": [
        "noun"
    ],
    "village": [
        "noun"
    ],
    "store": [
        "noun"
    ],
    "supermarket": [
        "noun"
    ],
    "bakery": [
        "noun"
    ],
    "restaurant": [
        "noun"
    ],
    "neighborhood": [
        "noun"
    ],
    "household": [
        "noun"
    ],
    "family": [
        "noun"
    ],
    "parent": [
        "noun"
    ],
    "mother": [
        "noun"
    ],
    "father": [
        "noun"
    ],
    "child": [
        "noun"
    ],
    "son": [
        "noun"
    ],
    "daughter": [
        "noun"
    ],
    "brother": [
        "noun"
    ],
    "sister": [
        "noun"
    ],
    "grandparent": [
        "noun"
    ],
    "grandmother": [
        "noun"
    ],
    "grandfather": [
        "noun"
    ],
    "grandson": [
        "noun"
    ],
    "granddaughter": [
        "noun"
    ],
    "uncle": [
        "noun"
    ],
    "aunt": [
        "noun"
    ],
    "cousin": [
        "noun"
    ],
    "nephew": [
        "noun"
    ],
    "niece": [
        "noun"
    ],
    "friend": [
        "noun"
    ],
    "enemy": [
        "noun"
    ],
    "stranger": [
        "noun"
    ],
    "guest": [
        "noun"
    ],
    "host": [
        "noun"
    ],
    "customer": [
        "noun"
    ],
    "client": [
        "noun"
    ],
    "farmer": [
        "noun"
    ],
    "gardener": [
        "noun"
    ],
    "cook": [
        "noun",
        "vb",
        "vbp"
    ],
    "fisherman": [
        "noun"
    ],
    "teacher": [
        "noun"
    ],
    "professor": [
        "noun"
    ],
    "student": [
        "noun"
    ],
    "doctor": [
        "noun"
    ],
    "nurse": [
        "noun"
    ],
    "patient": [
        "noun"
    ],
    "balloon": [
        "noun"
    ],
    "jar": [
        "noun"
    ],
    "automobile": [
        "noun"
    ],
    "park": [
        "noun"
    ],
    "comet": [
        "noun"
    ],
    "star": [
        "noun"
    ],
    "rabbit": [
        "noun"
    ],
    "veil": [
        "noun"
    ],
    "truck": [
        "noun"
    ],
    "racecar": [
        "noun"
    ],
    "pond": [
        "noun"
    ],
    "fairy": [
        "noun"
    ],
    "swing": [
        "noun"
    ],
    "bush": [
        "noun"
    ],
    "map": [
        "noun"
    ],
    "machine": [
        "noun"
    ],
    "voice": [
        "noun"
    ],
    "stroke": [
        "noun"
    ],
    "sack": [
        "noun"
    ],
    "key": [
        "noun"
    ],
    "value": [
        "noun"
    ],
    "wind": [
        "noun"
    ],
    "treat": [
        "noun"
    ],
    "race": [
        "noun"
    ],
    "box": [
        "noun"
    ],
    "shirt": [
        "noun"
    ],
    "jail": [
        "noun"
    ],
    "rainbow": [
        "noun"
    ],
    "garage": [
        "noun"
    ],
    "birthday": [
        "noun"
    ],
    "sausage": [
        "noun"
    ],
    "birdcage": [
        "noun"
    ],
    "bunny": [
        "noun"
    ],
    "nest": [
        "noun"
    ],
    "egg": [
        "noun"
    ],
    "robot": [
        "noun"
    ],
    "castle": [
        "noun"
    ],
    "tag": [
        "noun"
    ],
    "hook": [
        "noun"
    ],
    "button": [
        "noun"
    ],
    "firework": [
        "noun"
    ],
    "block": [
        "noun"
    ],
    "crayon": [
        "noun"
    ],
    "hanger": [
        "noun"
    ],
    "janitor": [
        "noun"
    ],
    "curve": [
        "noun"
    ],
    "jacket": [
        "noun"
    ],
    "sweater": [
        "noun"
    ],
    "dress": [
        "noun"
    ],
    "blouse": [
        "noun"
    ],
    "arrow": [
        "noun"
    ],
    "tub": [
        "noun"
    ],
    "plan": [
        "noun"
    ],
    "flashlight": [
        "noun"
    ],
    "tent": [
        "noun"
    ],
    "crane": [
        "noun"
    ],
    "sign": [
        "noun"
    ],
    "attic": [
        "noun"
    ],
    "spider": [
        "noun"
    ],
    "blueberry": [
        "noun"
    ],
    "strawberry": [
        "noun"
    ],
    "raspberry": [
        "noun"
    ],
    "huckleberry": [
        "noun"
    ],
    "blackberry": [
        "noun"
    ],
    "orange": [
        "noun"
    ],
    "wish": [
        "noun",
        "vb_np",
        "vbp_np"
    ],
    "laugh": [
        "noun",
        "vb",
        "vbp"
    ],
    "shop": [
        "noun"
    ],
    "hug": [
        "noun"
    ],
    "word": [
        "noun"
    ],
    "verb": [
        "noun"
    ],
    "noun": [
        "noun"
    ],
    "adjective": [
        "noun"
    ],
    "adverb": [
        "noun"
    ],
    "preposition": [
        "noun"
    ],
    "pole": [
        "noun"
    ],
    "reward": [
        "noun"
    ],
    "loss": [
        "noun"
    ],
    "agent": [
        "noun"
    ],
    "whistle": [
        "noun"
    ],
    "collar": [
        "noun"
    ],
    "belt": [
        "noun"
    ],
    "slide": [
        "noun"
    ],
    "coaster": [
        "noun"
    ],
    "skull": [
        "noun"
    ],
    "tibia": [
        "noun"
    ],
    "pelvis": [
        "noun"
    ],
    "femur": [
        "noun"
    ],
    "clavicle": [
        "noun"
    ],
    "collarbone": [
        "noun"
    ],
    "vertebra": [
        "noun"
    ],
    "phalange": [
        "noun"
    ],
    "rib": [
        "noun"
    ],
    "sternum": [
        "noun"
    ],
    "basket": [
        "noun"
    ],
    "blade": [
        "noun"
    ],
    "blow": [
        "noun"
    ],
    "boat": [
        "noun"
    ],
    "body": [
        "noun"
    ],
    "carrot": [
        "noun"
    ],
    "branch": [
        "noun"
    ],
    "bomb": [
        "noun"
    ],
    "boy": [
        "noun"
    ],
    "girl": [
        "noun"
    ],
    "border": [
        "noun"
    ],
    "bottom": [
        "noun"
    ],
    "brain": [
        "noun"
    ],
    "bottle": [
        "noun"
    ],
    "brush": [
        "noun"
    ],
    "budget": [
        "noun"
    ],
    "concept": [
        "noun"
    ],
    "sun": [
        "noun"
    ],
    "moon": [
        "noun"
    ],
    "earth": [
        "noun"
    ],
    "hail": [
        "noun"
    ],
    "favorite": [
        "noun"
    ],
    "home": [
        "noun"
    ],
    "apples": [
        "noun"
    ],
    "bananas": [
        "noun"
    ],
    "cars": [
        "noun"
    ],
    "houses": [
        "noun"
    ],
    "trees": [
        "noun"
    ],
    "flowers": [
        "noun"
    ],
    "daisies": [
        "noun"
    ],
    "bees": [
        "noun"
    ],
    "dogs": [
        "noun"
    ],
    "cats": [
        "noun"
    ],
    "cows": [
        "noun"
    ],
    "pigs": [
        "noun"
    ],
    "horses": [
        "noun"
    ],
    "chickens": [
        "noun"
    ],
    "birds": [
        "noun"
    ],
    "hummingbirds": [
        "noun"
    ],
    "rhinoceroses": [
        "noun"
    ],
    "elephants": [
        "noun"
    ],
    "fishes": [
        "noun",
        "vbz"
    ],
    "whales": [
        "noun"
    ],
    "octopuses": [
        "noun"
    ],
    "books": [
        "noun"
    ],
    "pens": [
        "noun"
    ],
    "pencils": [
        "noun"
    ],
    "computers": [
        "noun"
    ],
    "phones": [
        "noun"
    ],
    "televisions": [
        "noun"
    ],
    "radios": [
        "noun"
    ],
    "newspapers": [
        "noun"
    ],
    "magazines": [
        "noun"
    ],
    "letters": [
        "noun"
    ],
    "emails": [
        "noun"
    ],
    "pictures": [
        "noun"
    ],
    "photographs": [
        "noun"
    ],
    "videos": [
        "noun"
    ],
    "movies": [
        "noun"
    ],
    "musics": [
        "noun"
    ],
    "songs": [
        "noun"
    ],
    "dances": [
        "noun",
        "vbz"
    ],
    "games": [
        "noun"
    ],
    "toys": [
        "noun"
    ],
    "snowmans": [
        "noun"
    ],
    "balls": [
        "noun"
    ],
    "dolls": [
        "noun"
    ],
    "carpets": [
        "noun"
    ],
    "floors": [
        "noun"
    ],
    "ceilings": [
        "noun"
    ],
    "walls": [
        "noun"
    ],
    "windows": [
        "noun"
    ],
    "doors": [
        "noun"
    ],
    "roofs": [
        "noun"
    ],
    "stairs": [
        "noun"
    ],
    "steps": [
        "noun"
    ],
    "halls": [
        "noun"
    ],
    "rooms": [
        "noun"
    ],
    "kitchens": [
        "noun"
    ],
    "stoves": [
        "noun"
    ],
    "spatulas": [
        "noun"
    ],
    "spoons": [
        "noun"
    ],
    "knifes": [
        "noun"
    ],
    "forks": [
        "noun"
    ],
    "bowls": [
        "noun"
    ],
    "plates": [
        "noun"
    ],
    "cups": [
        "noun"
    ],
    "glasses": [
        "noun"
    ],
    "mugs": [
        "noun"
    ],
    "platters": [
        "noun"
    ],
    "dishes": [
        "noun"
    ],
    "vegetables": [
        "noun"
    ],
    "meats": [
        "noun"
    ],
    "grains": [
        "noun"
    ],
    "bathrooms": [
        "noun"
    ],
    "bedrooms": [
        "noun"
    ],
    "beds": [
        "noun"
    ],
    "tables": [
        "noun"
    ],
    "chairs": [
        "noun"
    ],
    "sofas": [
        "noun"
    ],
    "couches": [
        "noun"
    ],
    "desks": [
        "noun"
    ],
    "shelfs": [
        "noun"
    ],
    "drawers": [
        "noun"
    ],
    "cabinets": [
        "noun"
    ],
    "closets": [
        "noun"
    ],
    "mirrors": [
        "noun"
    ],
    "sinks": [
        "noun"
    ],
    "toilets": [
        "noun"
    ],
    "bathtubs": [
        "noun"
    ],
    "showers": [
        "noun"
    ],
    "towels": [
        "noun"
    ],
    "soaps": [
        "noun"
    ],
    "shampoos": [
        "noun"
    ],
    "toothbrushes": [
        "noun"
    ],
    "toothpastes": [
        "noun"
    ],
    "hairbrushes": [
        "noun"
    ],
    "lightbulbs": [
        "noun"
    ],
    "lamps": [
        "noun"
    ],
    "candles": [
        "noun"
    ],
    "gardens": [
        "noun"
    ],
    "yards": [
        "noun"
    ],
    "streets": [
        "noun"
    ],
    "roads": [
        "noun"
    ],
    "highways": [
        "noun"
    ],
    "bridges": [
        "noun"
    ],
    "tunnels": [
        "noun"
    ],
    "rivers": [
        "noun"
    ],
    "lakes": [
        "noun"
    ],
    "oceans": [
        "noun"
    ],
    "seas": [
        "noun"
    ],
    "beaches": [
        "noun"
    ],
    "mountains": [
        "noun"
    ],
    "hills": [
        "noun"
    ],
    "valleys": [
        "noun"
    ],
    "forests": [
        "noun"
    ],
    "jungles": [
        "noun"
    ],
    "deserts": [
        "noun"
    ],
    "islands": [
        "noun"
    ],
    "continents": [
        "noun"
    ],
    "countries": [
        "noun"
    ],
    "states": [
        "noun"
    ],
    "cities": [
        "noun"
    ],
    "towns": [
        "noun"
    ],
    "villages": [
        "noun"
    ],
    "stores": [
        "noun"
    ],
    "supermarkets": [
        "noun"
    ],
    "bakeries": [
        "noun"
    ],
    "restaurants": [
        "noun"
    ],
    "neighborhoods": [
        "noun"
    ],
    "households": [
        "noun"
    ],
    "families": [
        "noun"
    ],
    "parents": [
        "noun"
    ],
    "mothers": [
        "noun"
    ],
    "fathers": [
        "noun"
    ],
    "children": [
        "noun"
    ],
    "sons": [
        "noun"
    ],
    "daughters": [
        "noun"
    ],
    "brothers": [
        "noun"
    ],
    "sisters": [
        "noun"
    ],
    "grandparents": [
        "noun"
    ],
    "grandmothers": [
        "noun"
    ],
    "grandfathers": [
        "noun"
    ],
    "grandsons": [
        "noun"
    ],
    "granddaughters": [
        "noun"
    ],
    "uncles": [
        "noun"
    ],
    "aunts": [
        "noun"
    ],
    "cousins": [
        "noun"
    ],
    "nephews": [
        "noun"
    ],
    "nieces": [
        "noun"
    ],
    "friends": [
        "noun"
    ],
    "enemies": [
        "noun"
    ],
    "strangers": [
        "noun"
    ],
    "guests": [
        "noun"
    ],
    "hosts": [
        "noun"
    ],
    "customers": [
        "noun"
    ],
    "clients": [
        "noun"
    ],
    "farmers": [
        "noun"
    ],
    "gardeners": [
        "noun"
    ],
    "cooks": [
        "noun",
        "vbz"
    ],
    "fishermans": [
        "noun"
    ],
    "teachers": [
        "noun"
    ],
    "professors": [
        "noun"
    ],
    "students": [
        "noun"
    ],
    "doctors": [
        "noun"
    ],
    "nurses": [
        "noun"
    ],
    "patients": [
        "noun"
    ],
    "balloons": [
        "noun"
    ],
    "jars": [
        "noun"
    ],
    "automobiles": [
        "noun"
    ],
    "parks": [
        "noun"
    ],
    "comets": [
        "noun"
    ],
    "stars": [
        "noun"
    ],
    "rabbits": [
        "noun"
    ],
    "veils": [
        "noun"
    ],
    "trucks": [
        "noun"
    ],
    "racecars": [
        "noun"
    ],
    "ponds": [
        "noun"
    ],
    "fairies": [
        "noun"
    ],
    "swings": [
        "noun"
    ],
    "bushes": [
        "noun"
    ],
    "maps": [
        "noun"
    ],
    "machines": [
        "noun"
    ],
    "voices": [
        "noun"
    ],
    "strokes": [
        "noun"
    ],
    "sacks": [
        "noun"
    ],
    "keys": [
        "noun"
    ],
    "values": [
        "noun"
    ],
    "winds": [
        "noun"
    ],
    "treats": [
        "noun"
    ],
    "races": [
        "noun"
    ],
    "boxes": [
        "noun"
    ],
    "shirts": [
        "noun"
    ],
    "jails": [
        "noun"
    ],
    "rainbows": [
        "noun"
    ],
    "garages": [
        "noun"
    ],
    "birthdays": [
        "noun"
    ],
    "candies": [
        "noun"
    ],
    "stuffs": [
        "noun"
    ],
    "sausages": [
        "noun"
    ],
    "birdcages": [
        "noun"
    ],
    "bunnies": [
        "noun"
    ],
    "nests": [
        "noun"
    ],
    "eggs": [
        "noun"
    ],
    "yogurts": [
        "noun"
    ],
    "robots": [
        "noun"
    ],
    "castles": [
        "noun"
    ],
    "tags": [
        "noun"
    ],
    "honeys": [
        "noun"
    ],
    "hooks": [
        "noun"
    ],
    "buttons": [
        "noun"
    ],
    "fireworks": [
        "noun"
    ],
    "blocks": [
        "noun"
    ],
    "crayons": [
        "noun"
    ],
    "hangers": [
        "noun"
    ],
    "janitors": [
        "noun"
    ],
    "creams": [
        "noun"
    ],
    "curves": [
        "noun"
    ],
    "jackets": [
        "noun"
    ],
    "sweaters": [
        "noun"
    ],
    "dresses": [
        "noun"
    ],
    "blouses": [
        "noun"
    ],
    "arrows": [
        "noun"
    ],
    "tubs": [
        "noun"
    ],
    "plans": [
        "noun"
    ],
    "advices": [
        "noun"
    ],
    "flashlights": [
        "noun"
    ],
    "tents": [
        "noun"
    ],
    "cranes": [
        "noun"
    ],
    "signs": [
        "noun"
    ],
    "attics": [
        "noun"
    ],
    "spiders": [
        "noun"
    ],
    "blueberries": [
        "noun"
    ],
    "strawberries": [
        "noun"
    ],
    "raspberries": [
        "noun"
    ],
    "huckleberries": [
        "noun"
    ],
    "blackberries": [
        "noun"
    ],
    "oranges": [
        "noun"
    ],
    "wishes": [
        "noun",
        "vbz_np"
    ],
    "laughs": [
        "noun",
        "vbz"
    ],
    "shops": [
        "noun"
    ],
    "hugs": [
        "noun"
    ],
    "words": [
        "noun"
    ],
    "verbs": [
        "noun"
    ],
    "nouns": [
        "noun"
    ],
    "adjectives": [
        "noun"
    ],
    "adverbs": [
        "noun"
    ],
    "prepositions": [
        "noun"
    ],
    "poles": [
        "noun"
    ],
    "rewards": [
        "noun"
    ],
    "losses": [
        "noun"
    ],
    "agents": [
        "noun"
    ],
    "whistles": [
        "noun"
    ],
    "collars": [
        "noun"
    ],
    "belts": [
        "noun"
    ],
    "slides": [
        "noun"
    ],
    "coasters": [
        "noun"
    ],
    "skulls": [
        "noun"
    ],
    "tibias": [
        "noun"
    ],
    "pelvises": [
        "noun"
    ],
    "femurs": [
        "noun"
    ],
    "clavicles": [
        "noun"
    ],
    "collarbones": [
        "noun"
    ],
    "vertebras": [
        "noun"
    ],
    "phalanges": [
        "noun"
    ],
    "ribs": [
        "noun"
    ],
    "sternums": [
        "noun"
    ],
    "baskets": [
        "noun"
    ],
    "blades": [
        "noun"
    ],
    "blows": [
        "noun"
    ],
    "boats": [
        "noun"
    ],
    "bodies": [
        "noun"
    ],
    "carrots": [
        "noun"
    ],
    "branches": [
        "noun"
    ],
    "bombs": [
        "noun"
    ],
    "boys": [
        "noun"
    ],
    "girls": [
        "noun"
    ],
    "borders": [
        "noun"
    ],
    "bottoms": [
        "noun"
    ],
    "brains": [
        "noun"
    ],
    "bottles": [
        "noun"
    ],
    "brushes": [
        "noun"
    ],
    "budgets": [
        "noun"
    ],
    "concepts": [
        "noun"
    ],
    "suns": [
        "noun"
    ],
    "moons": [
        "noun"
    ],
    "earths": [
        "noun"
    ],
    "rains": [
        "noun"
    ],
    "snows": [
        "noun"
    ],
    "hails": [
        "noun"
    ],
    "favorites": [
        "noun"
    ],
    "homes": [
        "noun"
    ],
    "be": [
        "vb",
        "vb_ap",
        "vb_vbg_cl",
        "vb_np"
    ],
    "exist": [
        "vb",
        "vbp"
    ],
    "ache": [
        "vb",
        "vbp"
    ],
    "agonize": [
        "vb",
        "vbp"
    ],
    "atrophy": [
        "vb",
        "vbp"
    ],
    "babble": [
        "vb",
        "vbp"
    ],
    "bark": [
        "vb",
        "vbp"
    ],
    "beam": [
        "vb",
        "vbp"
    ],
    "behave": [
        "vb",
        "vbp"
    ],
    "belch": [
        "vb",
        "vbp"
    ],
    "bellow": [
        "vb",
        "vbp"
    ],
    "sing": [
        "vb",
        "vbp",
        "vb_np",
        "vbp_np"
    ],
    "speak": [
        "vb",
        "vbp"
    ],
    "slip": [
        "vb",
        "vbp"
    ],
    "smile": [
        "vb",
        "vbp"
    ],
    "snarl": [
        "vb",
        "vbp"
    ],
    "stumble": [
        "vb",
        "vbp"
    ],
    "swim": [
        "vb",
        "vbp"
    ],
    "talk": [
        "vb",
        "vbp"
    ],
    "think": [
        "vb",
        "vbp",
        "vb_declarative_cl",
        "vbp_declarative_cl"
    ],
    "caw": [
        "vb",
        "vbp"
    ],
    "choke": [
        "vb",
        "vbp"
    ],
    "clap": [
        "vb",
        "vbp"
    ],
    "climb": [
        "vb",
        "vbp"
    ],
    "crawl": [
        "vb",
        "vbp"
    ],
    "cry": [
        "vb",
        "vbp"
    ],
    "dive": [
        "vb",
        "vbp"
    ],
    "dream": [
        "vb",
        "vbp"
    ],
    "drink": [
        "vb",
        "vbp",
        "vb_np",
        "vbp_np"
    ],
    "clamor": [
        "vb",
        "vbp"
    ],
    "clatter": [
        "vb",
        "vbp"
    ],
    "clink": [
        "vb",
        "vbp"
    ],
    "cool": [
        "vb",
        "vbp"
    ],
    "cough": [
        "vb",
        "vbp"
    ],
    "crack": [
        "vb",
        "vbp"
    ],
    "crash": [
        "vb",
        "vbp"
    ],
    "creak": [
        "vb",
        "vbp"
    ],
    "croak": [
        "vb",
        "vbp"
    ],
    "crow": [
        "vb",
        "vbp"
    ],
    "darken": [
        "vb",
        "vbp"
    ],
    "dazzle": [
        "vb",
        "vbp"
    ],
    "drip": [
        "vb",
        "vbp"
    ],
    "ding": [
        "vb",
        "vbp"
    ],
    "daydream": [
        "vb",
        "vbp"
    ],
    "doze": [
        "vb",
        "vbp"
    ],
    "drowse": [
        "vb",
        "vbp"
    ],
    "drift": [
        "vb",
        "vbp"
    ],
    "drown": [
        "vb",
        "vbp"
    ],
    "dwell": [
        "vb",
        "vbp"
    ],
    "drool": [
        "vb",
        "vbp"
    ],
    "escape": [
        "vb",
        "vbp"
    ],
    "faint": [
        "vb",
        "vbp"
    ],
    "fade": [
        "vb",
        "vbp"
    ],
    "float": [
        "vb",
        "vbp"
    ],
    "flail": [
        "vb",
        "vbp"
    ],
    "fly": [
        "vb",
        "vbp"
    ],
    "flash": [
        "vb",
        "vbp"
    ],
    "frown": [
        "vb",
        "vbp"
    ],
    "focus": [
        "vb",
        "vbp"
    ],
    "feast": [
        "vb",
        "vbp"
    ],
    "gasp": [
        "vb",
        "vbp"
    ],
    "giggle": [
        "vb",
        "vbp"
    ],
    "glare": [
        "vb",
        "vbp"
    ],
    "glint": [
        "vb",
        "vbp"
    ],
    "glisten": [
        "vb",
        "vbp"
    ],
    "glimmer": [
        "vb",
        "vbp"
    ],
    "glow": [
        "vb",
        "vbp"
    ],
    "go": [
        "vb",
        "vbp"
    ],
    "growl": [
        "vb",
        "vbp"
    ],
    "gurgle": [
        "vb",
        "vbp"
    ],
    "gush": [
        "vb",
        "vbp"
    ],
    "help": [
        "vb",
        "vbp",
        "vb_bare_inf_cl",
        "vbp_bare_inf_cl",
        "vb_np",
        "vbp_np",
        "vb_np_to_inf_cl",
        "vbp_np_to_inf_cl",
        "vb_np_np",
        "vbp_np_np"
    ],
    "hiss": [
        "vb",
        "vbp"
    ],
    "howl": [
        "vb",
        "vbp"
    ],
    "hesitate": [
        "vb",
        "vbp"
    ],
    "hide": [
        "vb",
        "vbp"
    ],
    "hike": [
        "vb",
        "vbp"
    ],
    "honk": [
        "vb",
        "vbp"
    ],
    "hoot": [
        "vb",
        "vbp"
    ],
    "holler": [
        "vb",
        "vbp"
    ],
    "improve": [
        "vb",
        "vbp"
    ],
    "inch": [
        "vb",
        "vbp"
    ],
    "increase": [
        "vb",
        "vbp"
    ],
    "insist": [
        "vb",
        "vbp"
    ],
    "iron": [
        "vb",
        "vbp"
    ],
    "itch": [
        "vb",
        "vbp"
    ],
    "jangle": [
        "vb",
        "vbp"
    ],
    "jingle": [
        "vb",
        "vbp"
    ],
    "jog": [
        "vb",
        "vbp"
    ],
    "kick": [
        "vb",
        "vbp",
        "vb_np",
        "vbp_np"
    ],
    "kneel": [
        "vb",
        "vbp"
    ],
    "leak": [
        "vb",
        "vbp"
    ],
    "lighten": [
        "vb",
        "vbp"
    ],
    "listen": [
        "vb",
        "vbp"
    ],
    "load": [
        "vb",
        "vbp"
    ],
    "look": [
        "vb",
        "vbp",
        "vb_ap",
        "vbp_ap"
    ],
    "limp": [
        "vb",
        "vbp"
    ],
    "lose": [
        "vb",
        "vbp"
    ],
    "lurk": [
        "vb",
        "vbp"
    ],
    "lurch": [
        "vb",
        "vbp"
    ],
    "march": [
        "vb",
        "vbp"
    ],
    "meander": [
        "vb",
        "vbp"
    ],
    "melt": [
        "vb",
        "vbp"
    ],
    "mew": [
        "vb",
        "vbp"
    ],
    "meow": [
        "vb",
        "vbp"
    ],
    "moan": [
        "vb",
        "vbp"
    ],
    "moo": [
        "vb",
        "vbp"
    ],
    "mumble": [
        "vb",
        "vbp"
    ],
    "murmur": [
        "vb",
        "vbp"
    ],
    "mutter": [
        "vb",
        "vbp"
    ],
    "walk": [
        "vb",
        "vbp"
    ],
    "play": [
        "vb",
        "vbp",
        "vb_np",
        "vbp_np"
    ],
    "smoked": [
        "vbd",
        "vbn"
    ],
    "existed": [
        "vbd",
        "vbn"
    ],
    "ached": [
        "vbd",
        "vbn"
    ],
    "agonized": [
        "vbd",
        "vbn"
    ],
    "atrophied": [
        "vbd",
        "vbn"
    ],
    "babbled": [
        "vbd",
        "vbn"
    ],
    "barked": [
        "vbd",
        "vbn"
    ],
    "beamed": [
        "vbd",
        "vbn"
    ],
    "behaved": [
        "vbd",
        "vbn"
    ],
    "belched": [
        "vbd",
        "vbn"
    ],
    "bellowed": [
        "vbd",
        "vbn"
    ],
    "sang": [
        "vbd",
        "vbd_np"
    ],
    "spoke": [
        "vbd"
    ],
    "sliped": [
        "vbd",
        "vbn"
    ],
    "smiled": [
        "vbd",
        "vbn"
    ],
    "snarled": [
        "vbd",
        "vbn"
    ],
    "laughed": [
        "vbd",
        "vbn"
    ],
    "stumbled": [
        "vbd",
        "vbn"
    ],
    "swimed": [
        "vbd",
        "vbn"
    ],
    "talked": [
        "vbd",
        "vbn"
    ],
    "thought": [
        "vbd",
        "vbn",
        "vbd_declarative_cl",
        "vbn_declarative_cl"
    ],
    "cawed": [
        "vbd",
        "vbn"
    ],
    "choked": [
        "vbd",
        "vbn"
    ],
    "claped": [
        "vbd",
        "vbn"
    ],
    "climbed": [
        "vbd",
        "vbn"
    ],
    "crawled": [
        "vbd",
        "vbn"
    ],
    "cried": [
        "vbd",
        "vbn"
    ],
    "danced": [
        "vbd",
        "vbn"
    ],
    "dived": [
        "vbd",
        "vbn"
    ],
    "dreamed": [
        "vbd",
        "vbn"
    ],
    "drank": [
        "vbd",
        "vbd_np"
    ],
    "clamored": [
        "vbd",
        "vbn"
    ],
    "clattered": [
        "vbd",
        "vbn"
    ],
    "clinked": [
        "vbd",
        "vbn"
    ],
    "cooled": [
        "vbd",
        "vbn"
    ],
    "cooked": [
        "vbd",
        "vbn"
    ],
    "coughed": [
        "vbd",
        "vbn"
    ],
    "cracked": [
        "vbd",
        "vbn"
    ],
    "crashed": [
        "vbd",
        "vbn"
    ],
    "creaked": [
        "vbd",
        "vbn"
    ],
    "croaked": [
        "vbd",
        "vbn"
    ],
    "crowed": [
        "vbd",
        "vbn"
    ],
    "darkened": [
        "vbd",
        "vbn"
    ],
    "dazzled": [
        "vbd",
        "vbn"
    ],
    "driped": [
        "vbd",
        "vbn"
    ],
    "dinged": [
        "vbd",
        "vbn"
    ],
    "daydreamed": [
        "vbd",
        "vbn"
    ],
    "dozed": [
        "vbd",
        "vbn"
    ],
    "drowsed": [
        "vbd",
        "vbn"
    ],
    "drifted": [
        "vbd",
        "vbn"
    ],
    "drowned": [
        "vbd",
        "vbn"
    ],
    "dwelled": [
        "vbd",
        "vbn"
    ],
    "drooled": [
        "vbd",
        "vbn"
    ],
    "escaped": [
        "vbd",
        "vbn"
    ],
    "fainted": [
        "vbd",
        "vbn"
    ],
    "faded": [
        "vbd",
        "vbn"
    ],
    "fished": [
        "vbd",
        "vbn"
    ],
    "floated": [
        "vbd",
        "vbn"
    ],
    "flailed": [
        "vbd",
        "vbn"
    ],
    "flied": [
        "vbd",
        "vbn"
    ],
    "flashed": [
        "vbd",
        "vbn"
    ],
    "frowned": [
        "vbd",
        "vbn"
    ],
    "focused": [
        "vbd",
        "vbn"
    ],
    "feasted": [
        "vbd",
        "vbn"
    ],
    "gasped": [
        "vbd",
        "vbn"
    ],
    "giggled": [
        "vbd",
        "vbn"
    ],
    "glared": [
        "vbd",
        "vbn"
    ],
    "glinted": [
        "vbd",
        "vbn"
    ],
    "glistened": [
        "vbd",
        "vbn"
    ],
    "glimmered": [
        "vbd",
        "vbn"
    ],
    "glowed": [
        "vbd",
        "vbn"
    ],
    "went": [
        "vbd"
    ],
    "growled": [
        "vbd",
        "vbn"
    ],
    "gurgled": [
        "vbd",
        "vbn"
    ],
    "gushed": [
        "vbd",
        "vbn"
    ],
    "helped": [
        "vbd",
        "vbn",
        "vbd_bare_inf_cl",
        "vbn_bare_inf_cl",
        "vbd_np",
        "vbn_np",
        "vbd_np_to_inf_cl",
        "vbn_np_to_inf_cl",
        "vbd_np_np",
        "vbn_np_np"
    ],
    "hissed": [
        "vbd",
        "vbn"
    ],
    "howled": [
        "vbd",
        "vbn"
    ],
    "hesitated": [
        "vbd",
        "vbn"
    ],
    "hided": [
        "vbd",
        "vbn"
    ],
    "hiked": [
        "vbd",
        "vbn"
    ],
    "honked": [
        "vbd",
        "vbn"
    ],
    "hooted": [
        "vbd",
        "vbn"
    ],
    "hollered": [
        "vbd",
        "vbn"
    ],
    "improved": [
        "vbd",
        "vbn"
    ],
    "inched": [
        "vbd",
        "vbn"
    ],
    "increased": [
        "vbd",
        "vbn"
    ],
    "insisted": [
        "vbd",
        "vbn"
    ],
    "ironed": [
        "vbd",
        "vbn"
    ],
    "itched": [
        "vbd",
        "vbn"
    ],
    "jangled": [
        "vbd",
        "vbn"
    ],
    "jingled": [
        "vbd",
        "vbn"
    ],
    "joged": [
        "vbd",
        "vbn"
    ],
    "kicked": [
        "vbd",
        "vbn",
        "vbd_np",
        "vbn_np"
    ],
    "kneeled": [
        "vbd",
        "vbn"
    ],
    "leaked": [
        "vbd",
        "vbn"
    ],
    "lightened": [
        "vbd",
        "vbn"
    ],
    "listened": [
        "vbd",
        "vbn"
    ],
    "loaded": [
        "vbd",
        "vbn"
    ],
    "looked": [
        "vbd",
        "vbn",
        "vbd_ap",
        "vbn_ap"
    ],
    "limped": [
        "vbd",
        "vbn"
    ],
    "losed": [
        "vbd",
        "vbn"
    ],
    "lurked": [
        "vbd",
        "vbn"
    ],
    "lurched": [
        "vbd",
        "vbn"
    ],
    "marched": [
        "vbd",
        "vbn"
    ],
    "meandered": [
        "vbd",
        "vbn"
    ],
    "melted": [
        "vbd",
        "vbn"
    ],
    "mewed": [
        "vbd",
        "vbn"
    ],
    "meowed": [
        "vbd",
        "vbn"
    ],
    "moaned": [
        "vbd",
        "vbn"
    ],
    "mooed": [
        "vbd",
        "vbn"
    ],
    "mumbled": [
        "vbd",
        "vbn"
    ],
    "murmured": [
        "vbd",
        "vbn"
    ],
    "muttered": [
        "vbd",
        "vbn"
    ],
    "walked": [
        "vbd",
        "vbn"
    ],
    "played": [
        "vbd",
        "vbn",
        "vbd_np",
        "vbn_np"
    ],
    "been": [
        "vbn",
        "vbn_ap",
        "vbn_vbg_cl",
        "vbn_np"
    ],
    "sung": [
        "vbn",
        "vbn_np"
    ],
    "spoken": [
        "vbn"
    ],
    "drunk": [
        "vbn",
        "vbn_np"
    ],
    "gone": [
        "vbn"
    ],
    "being": [
        "vbg",
        "vbg_ap",
        "vbg_vbg_cl",
        "vbg_np"
    ],
    "smoking": [
        "vbg"
    ],
    "existing": [
        "vbg"
    ],
    "aching": [
        "vbg"
    ],
    "agonizing": [
        "vbg"
    ],
    "atrophying": [
        "vbg"
    ],
    "babbling": [
        "vbg"
    ],
    "barking": [
        "vbg"
    ],
    "beaming": [
        "vbg"
    ],
    "behaving": [
        "vbg"
    ],
    "belching": [
        "vbg"
    ],
    "bellowing": [
        "vbg"
    ],
    "singing": [
        "vbg",
        "vbg_np"
    ],
    "speaking": [
        "vbg"
    ],
    "sliping": [
        "vbg"
    ],
    "smiling": [
        "vbg"
    ],
    "snarling": [
        "vbg"
    ],
    "laughing": [
        "vbg"
    ],
    "stumbling": [
        "vbg"
    ],
    "swiming": [
        "vbg"
    ],
    "talking": [
        "vbg"
    ],
    "thinking": [
        "vbg",
        "vbg_declarative_cl"
    ],
    "cawing": [
        "vbg"
    ],
    "choking": [
        "vbg"
    ],
    "claping": [
        "vbg"
    ],
    "climbing": [
        "vbg"
    ],
    "crawling": [
        "vbg"
    ],
    "crying": [
        "vbg"
    ],
    "dancing": [
        "vbg"
    ],
    "diving": [
        "vbg"
    ],
    "dreaming": [
        "vbg"
    ],
    "drinking": [
        "vbg",
        "vbg_np"
    ],
    "clamoring": [
        "vbg"
    ],
    "clattering": [
        "vbg"
    ],
    "clinking": [
        "vbg"
    ],
    "cooling": [
        "vbg"
    ],
    "cooking": [
        "vbg"
    ],
    "coughing": [
        "vbg"
    ],
    "cracking": [
        "vbg"
    ],
    "crashing": [
        "vbg"
    ],
    "creaking": [
        "vbg"
    ],
    "croaking": [
        "vbg"
    ],
    "crowing": [
        "vbg"
    ],
    "darkening": [
        "vbg"
    ],
    "dazzling": [
        "vbg"
    ],
    "driping": [
        "vbg"
    ],
    "dinging": [
        "vbg"
    ],
    "daydreaming": [
        "vbg"
    ],
    "dozing": [
        "vbg"
    ],
    "drowsing": [
        "vbg"
    ],
    "drifting": [
        "vbg"
    ],
    "drowning": [
        "vbg"
    ],
    "dwelling": [
        "vbg"
    ],
    "drooling": [
        "vbg"
    ],
    "escaping": [
        "vbg"
    ],
    "fainting": [
        "vbg"
    ],
    "fading": [
        "vbg"
    ],
    "fishing": [
        "vbg"
    ],
    "floating": [
        "vbg"
    ],
    "flailing": [
        "vbg"
    ],
    "flying": [
        "vbg"
    ],
    "flashing": [
        "vbg"
    ],
    "frowning": [
        "vbg"
    ],
    "focusing": [
        "vbg"
    ],
    "feasting": [
        "vbg"
    ],
    "gasping": [
        "vbg"
    ],
    "giggling": [
        "vbg"
    ],
    "glaring": [
        "vbg"
    ],
    "glinting": [
        "vbg"
    ],
    "glistening": [
        "vbg"
    ],
    "glimmering": [
        "vbg"
    ],
    "glowing": [
        "vbg"
    ],
    "going": [
        "vbg"
    ],
    "growling": [
        "vbg"
    ],
    "gurgling": [
        "vbg"
    ],
    "gushing": [
        "vbg"
    ],
    "helping": [
        "vbg",
        "vbg_bare_inf_cl",
        "vbg_np",
        "vbg_np_to_inf_cl",
        "vbg_np_np"
    ],
    "hissing": [
        "vbg"
    ],
    "howling": [
        "vbg"
    ],
    "hesitating": [
        "vbg"
    ],
    "hiding": [
        "vbg"
    ],
    "hiking": [
        "vbg"
    ],
    "honking": [
        "vbg"
    ],
    "hooting": [
        "vbg"
    ],
    "hollering": [
        "vbg"
    ],
    "improving": [
        "vbg"
    ],
    "inching": [
        "vbg"
    ],
    "increasing": [
        "vbg"
    ],
    "insisting": [
        "vbg"
    ],
    "ironing": [
        "vbg"
    ],
    "itching": [
        "vbg"
    ],
    "jangling": [
        "vbg"
    ],
    "jingling": [
        "vbg"
    ],
    "joging": [
        "vbg"
    ],
    "kicking": [
        "vbg",
        "vbg_np"
    ],
    "kneeling": [
        "vbg"
    ],
    "leaking": [
        "vbg"
    ],
    "lightening": [
        "vbg"
    ],
    "listening": [
        "vbg"
    ],
    "loading": [
        "vbg"
    ],
    "looking": [
        "vbg",
        "vbg_ap"
    ],
    "limping": [
        "vbg"
    ],
    "losing": [
        "vbg"
    ],
    "lurking": [
        "vbg"
    ],
    "lurching": [
        "vbg"
    ],
    "marching": [
        "vbg"
    ],
    "meandering": [
        "vbg"
    ],
    "melting": [
        "vbg"
    ],
    "mewing": [
        "vbg"
    ],
    "meowing": [
        "vbg"
    ],
    "moaning": [
        "vbg"
    ],
    "mooing": [
        "vbg"
    ],
    "mumbling": [
        "vbg"
    ],
    "murmuring": [
        "vbg"
    ],
    "muttering": [
        "vbg"
    ],
    "walking": [
        "vbg"
    ],
    "playing": [
        "vbg",
        "vbg_np"
    ],
    "smokes": [
        "vbz"
    ],
    "exists": [
        "vbz"
    ],
    "aches": [
        "vbz"
    ],
    "agonizes": [
        "vbz"
    ],
    "atrophies": [
        "vbz"
    ],
    "babbles": [
        "vbz"
    ],
    "barks": [
        "vbz"
    ],
    "beams": [
        "vbz"
    ],
    "behaves": [
        "vbz"
    ],
    "belches": [
        "vbz"
    ],
    "bellows": [
        "vbz"
    ],
    "sings": [
        "vbz",
        "vbz_np"
    ],
    "speaks": [
        "vbz"
    ],
    "slips": [
        "vbz"
    ],
    "smiles": [
        "vbz"
    ],
    "snarls": [
        "vbz"
    ],
    "stumbles": [
        "vbz"
    ],
    "swims": [
        "vbz"
    ],
    "talks": [
        "vbz"
    ],
    "thinks": [
        "vbz",
        "vbz_declarative_cl"
    ],
    "caws": [
        "vbz"
    ],
    "chokes": [
        "vbz"
    ],
    "claps": [
        "vbz"
    ],
    "climbs": [
        "vbz"
    ],
    "crawls": [
        "vbz"
    ],
    "cries": [
        "vbz"
    ],
    "dives": [
        "vbz"
    ],
    "dreams": [
        "vbz"
    ],
    "drinks": [
        "vbz",
        "vbz_np"
    ],
    "clamors": [
        "vbz"
    ],
    "clatters": [
        "vbz"
    ],
    "clinks": [
        "vbz"
    ],
    "cools": [
        "vbz"
    ],
    "coughs": [
        "vbz"
    ],
    "cracks": [
        "vbz"
    ],
    "crashes": [
        "vbz"
    ],
    "creaks": [
        "vbz"
    ],
    "croaks": [
        "vbz"
    ],
    "crows": [
        "vbz"
    ],
    "darkens": [
        "vbz"
    ],
    "dazzles": [
        "vbz"
    ],
    "drips": [
        "vbz"
    ],
    "dings": [
        "vbz"
    ],
    "daydreams": [
        "vbz"
    ],
    "dozes": [
        "vbz"
    ],
    "drowses": [
        "vbz"
    ],
    "drifts": [
        "vbz"
    ],
    "drowns": [
        "vbz"
    ],
    "dwells": [
        "vbz"
    ],
    "drools": [
        "vbz"
    ],
    "escapes": [
        "vbz"
    ],
    "faints": [
        "vbz"
    ],
    "fades": [
        "vbz"
    ],
    "floats": [
        "vbz"
    ],
    "flails": [
        "vbz"
    ],
    "flies": [
        "vbz"
    ],
    "flashes": [
        "vbz"
    ],
    "frowns": [
        "vbz"
    ],
    "focuses": [
        "vbz"
    ],
    "feasts": [
        "vbz"
    ],
    "gasps": [
        "vbz"
    ],
    "giggles": [
        "vbz"
    ],
    "glares": [
        "vbz"
    ],
    "glints": [
        "vbz"
    ],
    "glistens": [
        "vbz"
    ],
    "glimmers": [
        "vbz"
    ],
    "glows": [
        "vbz"
    ],
    "goes": [
        "vbz"
    ],
    "growls": [
        "vbz"
    ],
    "gurgles": [
        "vbz"
    ],
    "gushes": [
        "vbz"
    ],
    "helps": [
        "vbz",
        "vbz_bare_inf_cl",
        "vbz_np",
        "vbz_np_to_inf_cl",
        "vbz_np_np"
    ],
    "hisses": [
        "vbz"
    ],
    "howls": [
        "vbz"
    ],
    "hesitates": [
        "vbz"
    ],
    "hides": [
        "vbz"
    ],
    "hikes": [
        "vbz"
    ],
    "honks": [
        "vbz"
    ],
    "hoots": [
        "vbz"
    ],
    "hollers": [
        "vbz"
    ],
    "improves": [
        "vbz"
    ],
    "inches": [
        "vbz"
    ],
    "increases": [
        "vbz"
    ],
    "insists": [
        "vbz"
    ],
    "irons": [
        "vbz"
    ],
    "itches": [
        "vbz"
    ],
    "jangles": [
        "vbz"
    ],
    "jingles": [
        "vbz"
    ],
    "jogs": [
        "vbz"
    ],
    "kicks": [
        "vbz",
        "vbz_np"
    ],
    "kneels": [
        "vbz"
    ],
    "leaks": [
        "vbz"
    ],
    "lightens": [
        "vbz"
    ],
    "listens": [
        "vbz"
    ],
    "loads": [
        "vbz"
    ],
    "looks": [
        "vbz",
        "vbz_ap"
    ],
    "limps": [
        "vbz"
    ],
    "loses": [
        "vbz"
    ],
    "lurks": [
        "vbz"
    ],
    "lurches": [
        "vbz"
    ],
    "marches": [
        "vbz"
    ],
    "meanders": [
        "vbz"
    ],
    "melts": [
        "vbz"
    ],
    "mews": [
        "vbz"
    ],
    "meows": [
        "vbz"
    ],
    "moans": [
        "vbz"
    ],
    "moos": [
        "vbz"
    ],
    "mumbles": [
        "vbz"
    ],
    "murmurs": [
        "vbz"
    ],
    "mutters": [
        "vbz"
    ],
    "walks": [
        "vbz"
    ],
    "plays": [
        "vbz",
        "vbz_np"
    ],
    "seem": [
        "vb_ap",
        "vbp_ap"
    ],
    "appear": [
        "vb_ap",
        "vbp_ap"
    ],
    "sound": [
        "vb_ap",
        "vbp_ap"
    ],
    "taste": [
        "vb_ap",
        "vbp_ap"
    ],
    "smell": [
        "vb_ap",
        "vbp_ap",
        "vb_np",
        "vbp_np"
    ],
    "feel": [
        "vb_ap",
        "vbp_ap",
        "vb_np",
        "vbp_np"
    ],
    "seemed": [
        "vbd_ap",
        "vbn_ap"
    ],
    "appeared": [
        "vbd_ap",
        "vbn_ap"
    ],
    "sounded": [
        "vbd_ap",
        "vbn_ap"
    ],
    "tasted": [
        "vbd_ap",
        "vbn_ap"
    ],
    "smelt": [
        "vbd_ap",
        "vbn_ap",
        "vbd_np",
        "vbn_np"
    ],
    "felt": [
        "vbd_ap",
        "vbn_ap",
        "vbd_np",
        "vbn_np"
    ],
    "seeming": [
        "vbg_ap"
    ],
    "appearing": [
        "vbg_ap"
    ],
    "sounding": [
        "vbg_ap"
    ],
    "tasting": [
        "vbg_ap"
    ],
    "smelling": [
        "vbg_ap",
        "vbg_np"
    ],
    "feeling": [
        "vbg_ap",
        "vbg_np"
    ],
    "seems": [
        "vbz_ap"
    ],
    "appears": [
        "vbz_ap"
    ],
    "sounds": [
        "vbz_ap"
    ],
    "tastes": [
        "vbz_ap"
    ],
    "smells": [
        "vbz_ap",
        "vbz_np"
    ],
    "feels": [
        "vbz_ap",
        "vbz_np"
    ],
    "want": [
        "vb_to_inf_cl",
        "vbp_to_inf_cl",
        "vb_np",
        "vbp_np",
        "vb_np_to_inf_cl",
        "vbp_np_to_inf_cl"
    ],
    "need": [
        "vb_to_inf_cl",
        "vbp_to_inf_cl",
        "vb_np",
        "vbp_np"
    ],
    "like": [
        "vb_to_inf_cl",
        "vbp_to_inf_cl",
        "vb_np",
        "vbp_np"
    ],
    "love": [
        "vb_to_inf_cl",
        "vbp_to_inf_cl",
        "vb_np",
        "vbp_np"
    ],
    "prefer": [
        "vb_to_inf_cl",
        "vbp_to_inf_cl"
    ],
    "know": [
        "vb_to_inf_cl",
        "vbp_to_inf_cl",
        "vb_declarative_cl",
        "vbp_declarative_cl",
        "vb_exclamative_cl",
        "vbp_exclamative_cl",
        "vb_interrogative_cl",
        "vbp_interrogative_cl",
        "vb_np",
        "vbp_np"
    ],
    "wanted": [
        "vbd_to_inf_cl",
        "vbn_to_inf_cl",
        "vbd_np",
        "vbn_np",
        "vbd_np_to_inf_cl",
        "vbn_np_to_inf_cl"
    ],
    "needed": [
        "vbd_to_inf_cl",
        "vbn_to_inf_cl",
        "vbd_np",
        "vbn_np"
    ],
    "liked": [
        "vbd_to_inf_cl",
        "vbn_to_inf_cl",
        "vbd_np",
        "vbn_np"
    ],
    "loved": [
        "vbd_to_inf_cl",
        "vbn_to_inf_cl",
        "vbd_np",
        "vbn_np"
    ],
    "prefered": [
        "vbd_to_inf_cl",
        "vbn_to_inf_cl"
    ],
    "knew": [
        "vbd_to_inf_cl",
        "vbd_declarative_cl",
        "vbd_exclamative_cl",
        "vbd_interrogative_cl",
        "vbd_np"
    ],
    "known": [
        "vbn_to_inf_cl",
        "vbn_declarative_cl",
        "vbn_exclamative_cl",
        "vbn_interrogative_cl",
        "vbn_np"
    ],
    "wanting": [
        "vbg_to_inf_cl",
        "vbg_np",
        "vbg_np_to_inf_cl"
    ],
    "needing": [
        "vbg_to_inf_cl",
        "vbg_np"
    ],
    "liking": [
        "vbg_to_inf_cl",
        "vbg_np"
    ],
    "loving": [
        "vbg_to_inf_cl",
        "vbg_np"
    ],
    "prefering": [
        "vbg_to_inf_cl"
    ],
    "knowing": [
        "vbg_to_inf_cl",
        "vbg_declarative_cl",
        "vbg_exclamative_cl",
        "vbg_interrogative_cl",
        "vbg_np"
    ],
    "wants": [
        "vbz_to_inf_cl",
        "vbz_np",
        "vbz_np_to_inf_cl"
    ],
    "needs": [
        "vbz_to_inf_cl",
        "vbz_np"
    ],
    "likes": [
        "vbz_to_inf_cl",
        "vbz_np"
    ],
    "loves": [
        "vbz_to_inf_cl",
        "vbz_np"
    ],
    "prefers": [
        "vbz_to_inf_cl"
    ],
    "knows": [
        "vbz_to_inf_cl",
        "vbz_declarative_cl",
        "vbz_exclamative_cl",
        "vbz_interrogative_cl",
        "vbz_np"
    ],
    "have": [
        "vb_vbn_cl",
        "vbp_vbn_cl",
        "vb_np",
        "vbp_np",
        "vb_np_bare_inf_cl",
        "vbp_np_bare_inf_cl"
    ],
    "had": [
        "vbd_vbn_cl",
        "vbn_vbn_cl",
        "vbd_np",
        "vbn_np",
        "vbd_np_bare_inf_cl",
        "vbn_np_bare_inf_cl"
    ],
    "having": [
        "vbg_vbn_cl",
        "vbg_np",
        "vbg_np_bare_inf_cl"
    ],
    "has": [
        "vbz_vbn_cl",
        "vbz_np",
        "vbz_np_bare_inf_cl"
    ],
    "doed": [
        "vbd_bare_inf_cl",
        "vbn_bare_inf_cl",
        "vbd_np",
        "vbn_np"
    ],
    "doing": [
        "vbg_bare_inf_cl",
        "vbg_np"
    ],
    "dos": [
        "vbz_bare_inf_cl",
        "vbz_np"
    ],
    "say": [
        "vb_declarative_cl",
        "vbp_declarative_cl",
        "vb_exclamative_cl",
        "vbp_exclamative_cl"
    ],
    "believe": [
        "vb_declarative_cl",
        "vbp_declarative_cl",
        "vb_np",
        "vbp_np"
    ],
    "understand": [
        "vb_declarative_cl",
        "vbp_declarative_cl",
        "vb_np",
        "vbp_np"
    ],
    "realize": [
        "vb_declarative_cl",
        "vbp_declarative_cl"
    ],
    "learn": [
        "vb_declarative_cl",
        "vbp_declarative_cl",
        "vb_np",
        "vbp_np"
    ],
    "remember": [
        "vb_declarative_cl",
        "vbp_declarative_cl",
        "vb_exclamative_cl",
        "vbp_exclamative_cl",
        "vb_np",
        "vbp_np"
    ],
    "forget": [
        "vb_declarative_cl",
        "vbp_declarative_cl",
        "vb_exclamative_cl",
        "vbp_exclamative_cl",
        "vb_np",
        "vbp_np"
    ],
    "imagine": [
        "vb_declarative_cl",
        "vbp_declarative_cl",
        "vb_np",
        "vbp_np"
    ],
    "agree": [
        "vb_declarative_cl",
        "vbp_declarative_cl"
    ],
    "promise": [
        "vb_declarative_cl",
        "vbp_declarative_cl",
        "vb_np",
        "vbp_np",
        "vb_np_np",
        "vbp_np_np"
    ],
    "hope": [
        "vb_declarative_cl",
        "vbp_declarative_cl",
        "vb_np",
        "vbp_np"
    ],
    "expect": [
        "vb_declarative_cl",
        "vbp_declarative_cl",
        "vb_np",
        "vbp_np"
    ],
    "worry": [
        "vb_declarative_cl",
        "vbp_declarative_cl",
        "vb_np",
        "vbp_np"
    ],
    "fear": [
        "vb_declarative_cl",
        "vbp_declarative_cl",
        "vb_np",
        "vbp_np"
    ],
    "inform": [
        "vb_declarative_cl",
        "vbp_declarative_cl"
    ],
    "complain": [
        "vb_declarative_cl",
        "vbp_declarative_cl"
    ],
    "prove": [
        "vb_declarative_cl",
        "vbp_declarative_cl",
        "vb_exclamative_cl",
        "vbp_exclamative_cl",
        "vb_interrogative_cl",
        "vbp_interrogative_cl"
    ],
    "recall": [
        "vb_declarative_cl",
        "vbp_declarative_cl",
        "vb_np",
        "vbp_np"
    ],
    "said": [
        "vbd_declarative_cl",
        "vbn_declarative_cl",
        "vbd_exclamative_cl",
        "vbn_exclamative_cl"
    ],
    "believed": [
        "vbd_declarative_cl",
        "vbn_declarative_cl",
        "vbd_np",
        "vbn_np"
    ],
    "understood": [
        "vbd_declarative_cl",
        "vbn_declarative_cl",
        "vbd_np",
        "vbn_np"
    ],
    "realized": [
        "vbd_declarative_cl",
        "vbn_declarative_cl"
    ],
    "learned": [
        "vbd_declarative_cl",
        "vbn_declarative_cl",
        "vbd_np",
        "vbn_np"
    ],
    "remembered": [
        "vbd_declarative_cl",
        "vbn_declarative_cl",
        "vbd_exclamative_cl",
        "vbn_exclamative_cl",
        "vbd_np",
        "vbn_np"
    ],
    "forgot": [
        "vbd_declarative_cl",
        "vbd_exclamative_cl",
        "vbd_np"
    ],
    "imagined": [
        "vbd_declarative_cl",
        "vbn_declarative_cl",
        "vbd_np",
        "vbn_np"
    ],
    "agreed": [
        "vbd_declarative_cl",
        "vbn_declarative_cl"
    ],
    "promised": [
        "vbd_declarative_cl",
        "vbn_declarative_cl",
        "vbd_np",
        "vbn_np",
        "vbd_np_np",
        "vbn_np_np"
    ],
    "hoped": [
        "vbd_declarative_cl",
        "vbn_declarative_cl",
        "vbd_np",
        "vbn_np"
    ],
    "expected": [
        "vbd_declarative_cl",
        "vbn_declarative_cl",
        "vbd_np",
        "vbn_np"
    ],
    "worried": [
        "vbd_declarative_cl",
        "vbn_declarative_cl",
        "vbd_np",
        "vbn_np"
    ],
    "feared": [
        "vbd_declarative_cl",
        "vbn_declarative_cl",
        "vbd_np",
        "vbn_np"
    ],
    "informed": [
        "vbd_declarative_cl",
        "vbn_declarative_cl"
    ],
    "complained": [
        "vbd_declarative_cl",
        "vbn_declarative_cl"
    ],
    "proved": [
        "vbd_declarative_cl",
        "vbn_declarative_cl",
        "vbd_exclamative_cl",
        "vbn_exclamative_cl",
        "vbd_interrogative_cl",
        "vbn_interrogative_cl"
    ],
    "recalled": [
        "vbd_declarative_cl",
        "vbn_declarative_cl",
        "vbd_np",
        "vbn_np"
    ],
    "forgotten": [
        "vbn_declarative_cl",
        "vbn_exclamative_cl",
        "vbn_np"
    ],
    "saying": [
        "vbg_declarative_cl",
        "vbg_exclamative_cl"
    ],
    "believing": [
        "vbg_declarative_cl",
        "vbg_np"
    ],
    "understanding": [
        "vbg_declarative_cl",
        "vbg_np"
    ],
    "realizing": [
        "vbg_declarative_cl"
    ],
    "learning": [
        "vbg_declarative_cl",
        "vbg_np"
    ],
    "remembering": [
        "vbg_declarative_cl",
        "vbg_exclamative_cl",
        "vbg_np"
    ],
    "forgetting": [
        "vbg_declarative_cl",
        "vbg_exclamative_cl",
        "vbg_np"
    ],
    "imagining": [
        "vbg_declarative_cl",
        "vbg_np"
    ],
    "agreing": [
        "vbg_declarative_cl"
    ],
    "promising": [
        "vbg_declarative_cl",
        "vbg_np",
        "vbg_np_np"
    ],
    "hoping": [
        "vbg_declarative_cl",
        "vbg_np"
    ],
    "expecting": [
        "vbg_declarative_cl",
        "vbg_np"
    ],
    "worrying": [
        "vbg_declarative_cl",
        "vbg_np"
    ],
    "fearing": [
        "vbg_declarative_cl",
        "vbg_np"
    ],
    "informing": [
        "vbg_declarative_cl"
    ],
    "complaining": [
        "vbg_declarative_cl"
    ],
    "proving": [
        "vbg_declarative_cl",
        "vbg_exclamative_cl",
        "vbg_interrogative_cl"
    ],
    "recalling": [
        "vbg_declarative_cl",
        "vbg_np"
    ],
    "says": [
        "vbz_declarative_cl",
        "vbz_exclamative_cl"
    ],
    "believes": [
        "vbz_declarative_cl",
        "vbz_np"
    ],
    "understands": [
        "vbz_declarative_cl",
        "vbz_np"
    ],
    "realizes": [
        "vbz_declarative_cl"
    ],
    "learns": [
        "vbz_declarative_cl",
        "vbz_np"
    ],
    "remembers": [
        "vbz_declarative_cl",
        "vbz_exclamative_cl",
        "vbz_np"
    ],
    "forgets": [
        "vbz_declarative_cl",
        "vbz_exclamative_cl",
        "vbz_np"
    ],
    "imagines": [
        "vbz_declarative_cl",
        "vbz_np"
    ],
    "agrees": [
        "vbz_declarative_cl"
    ],
    "promises": [
        "vbz_declarative_cl",
        "vbz_np",
        "vbz_np_np"
    ],
    "hopes": [
        "vbz_declarative_cl",
        "vbz_np"
    ],
    "expects": [
        "vbz_declarative_cl",
        "vbz_np"
    ],
    "worries": [
        "vbz_declarative_cl",
        "vbz_np"
    ],
    "fears": [
        "vbz_declarative_cl",
        "vbz_np"
    ],
    "informs": [
        "vbz_declarative_cl"
    ],
    "complains": [
        "vbz_declarative_cl"
    ],
    "proves": [
        "vbz_declarative_cl",
        "vbz_exclamative_cl",
        "vbz_interrogative_cl"
    ],
    "recalls": [
        "vbz_declarative_cl",
        "vbz_np"
    ],
    "tell": [
        "vb_exclamative_cl",
        "vbp_exclamative_cl",
        "vb_np",
        "vbp_np",
        "vb_np_to_inf_cl",
        "vbp_np_to_inf_cl",
        "vb_np_declarative_cl",
        "vbp_np_declarative_cl",
        "vb_np_exclamative_cl",
        "vbp_np_exclamative_cl",
        "vb_np_np",
        "vbp_np_np"
    ],
    "show": [
        "vb_exclamative_cl",
        "vbp_exclamative_cl",
        "vb_np",
        "vbp_np",
        "vb_np_declarative_cl",
        "vbp_np_declarative_cl",
        "vb_np_exclamative_cl",
        "vbp_np_exclamative_cl",
        "vb_np_np",
        "vbp_np_np"
    ],
    "explain": [
        "vb_exclamative_cl",
        "vbp_exclamative_cl",
        "vb_np",
        "vbp_np"
    ],
    "describe": [
        "vb_exclamative_cl",
        "vbp_exclamative_cl",
        "vb_np",
        "vbp_np"
    ],
    "demonstrate": [
        "vb_exclamative_cl",
        "vbp_exclamative_cl"
    ],
    "illustrate": [
        "vb_exclamative_cl",
        "vbp_exclamative_cl"
    ],
    "convince": [
        "vb_exclamative_cl",
        "vbp_exclamative_cl",
        "vb_np_declarative_cl",
        "vbp_np_declarative_cl"
    ],
    "persuade": [
        "vb_exclamative_cl",
        "vbp_exclamative_cl",
        "vb_np",
        "vbp_np",
        "vb_np_to_inf_cl",
        "vbp_np_to_inf_cl",
        "vb_np_declarative_cl",
        "vbp_np_declarative_cl",
        "vb_np_np",
        "vbp_np_np"
    ],
    "told": [
        "vbd_exclamative_cl",
        "vbn_exclamative_cl",
        "vbd_np",
        "vbn_np",
        "vbd_np_to_inf_cl",
        "vbn_np_to_inf_cl",
        "vbd_np_declarative_cl",
        "vbn_np_declarative_cl",
        "vbd_np_exclamative_cl",
        "vbn_np_exclamative_cl",
        "vbd_np_np",
        "vbn_np_np"
    ],
    "showed": [
        "vbd_exclamative_cl",
        "vbn_exclamative_cl",
        "vbd_np",
        "vbn_np",
        "vbd_np_declarative_cl",
        "vbn_np_declarative_cl",
        "vbd_np_exclamative_cl",
        "vbn_np_exclamative_cl",
        "vbd_np_np",
        "vbn_np_np"
    ],
    "explained": [
        "vbd_exclamative_cl",
        "vbn_exclamative_cl",
        "vbd_np",
        "vbn_np"
    ],
    "described": [
        "vbd_exclamative_cl",
        "vbn_exclamative_cl",
        "vbd_np",
        "vbn_np"
    ],
    "demonstrated": [
        "vbd_exclamative_cl",
        "vbn_exclamative_cl"
    ],
    "illustrated": [
        "vbd_exclamative_cl",
        "vbn_exclamative_cl"
    ],
    "convinced": [
        "vbd_exclamative_cl",
        "vbn_exclamative_cl",
        "vbd_np_declarative_cl",
        "vbn_np_declarative_cl"
    ],
    "persuaded": [
        "vbd_exclamative_cl",
        "vbn_exclamative_cl",
        "vbd_np",
        "vbn_np",
        "vbd_np_to_inf_cl",
        "vbn_np_to_inf_cl",
        "vbd_np_declarative_cl",
        "vbn_np_declarative_cl",
        "vbd_np_np",
        "vbn_np_np"
    ],
    "telling": [
        "vbg_exclamative_cl",
        "vbg_np",
        "vbg_np_to_inf_cl",
        "vbg_np_declarative_cl",
        "vbg_np_exclamative_cl",
        "vbg_np_np"
    ],
    "showing": [
        "vbg_exclamative_cl",
        "vbg_np",
        "vbg_np_declarative_cl",
        "vbg_np_exclamative_cl",
        "vbg_np_np"
    ],
    "explaining": [
        "vbg_exclamative_cl",
        "vbg_np"
    ],
    "describing": [
        "vbg_exclamative_cl",
        "vbg_np"
    ],
    "demonstrating": [
        "vbg_exclamative_cl"
    ],
    "illustrating": [
        "vbg_exclamative_cl"
    ],
    "convincing": [
        "vbg_exclamative_cl",
        "vbg_np_declarative_cl"
    ],
    "persuading": [
        "vbg_exclamative_cl",
        "vbg_np",
        "vbg_np_to_inf_cl",
        "vbg_np_declarative_cl",
        "vbg_np_np"
    ],
    "tells": [
        "vbz_exclamative_cl",
        "vbz_np",
        "vbz_np_to_inf_cl",
        "vbz_np_declarative_cl",
        "vbz_np_exclamative_cl",
        "vbz_np_np"
    ],
    "shows": [
        "vbz_exclamative_cl",
        "vbz_np",
        "vbz_np_declarative_cl",
        "vbz_np_exclamative_cl",
        "vbz_np_np"
    ],
    "explains": [
        "vbz_exclamative_cl",
        "vbz_np"
    ],
    "describes": [
        "vbz_exclamative_cl",
        "vbz_np"
    ],
    "demonstrates": [
        "vbz_exclamative_cl"
    ],
    "illustrates": [
        "vbz_exclamative_cl"
    ],
    "convinces": [
        "vbz_exclamative_cl",
        "vbz_np_declarative_cl"
    ],
    "persuades": [
        "vbz_exclamative_cl",
        "vbz_np",
        "vbz_np_to_inf_cl",
        "vbz_np_declarative_cl",
        "vbz_np_np"
    ],
    "wonder": [
        "vb_interrogative_cl",
        "vbp_interrogative_cl"
    ],
    "inqure": [
        "vb_interrogative_cl",
        "vbp_interrogative_cl"
    ],
    "ask": [
        "vb_interrogative_cl",
        "vbp_interrogative_cl",
        "vb_np",
        "vbp_np",
        "vb_np_to_inf_cl",
        "vbp_np_to_inf_cl",
        "vb_np_interrogative_cl",
        "vbp_np_interrogative_cl",
        "vb_np_np",
        "vbp_np_np"
    ],
    "discover": [
        "vb_interrogative_cl",
        "vbp_interrogative_cl"
    ],
    "wondered": [
        "vbd_interrogative_cl",
        "vbn_interrogative_cl"
    ],
    "inqured": [
        "vbd_interrogative_cl",
        "vbn_interrogative_cl"
    ],
    "asked": [
        "vbd_interrogative_cl",
        "vbn_interrogative_cl",
        "vbd_np",
        "vbn_np",
        "vbd_np_to_inf_cl",
        "vbn_np_to_inf_cl",
        "vbd_np_interrogative_cl",
        "vbn_np_interrogative_cl",
        "vbd_np_np",
        "vbn_np_np"
    ],
    "discovered": [
        "vbd_interrogative_cl",
        "vbn_interrogative_cl"
    ],
    "wondering": [
        "vbg_interrogative_cl"
    ],
    "inquring": [
        "vbg_interrogative_cl"
    ],
    "asking": [
        "vbg_interrogative_cl",
        "vbg_np",
        "vbg_np_to_inf_cl",
        "vbg_np_interrogative_cl",
        "vbg_np_np"
    ],
    "discovering": [
        "vbg_interrogative_cl"
    ],
    "wonders": [
        "vbz_interrogative_cl"
    ],
    "inqures": [
        "vbz_interrogative_cl"
    ],
    "asks": [
        "vbz_interrogative_cl",
        "vbz_np",
        "vbz_np_to_inf_cl",
        "vbz_np_interrogative_cl",
        "vbz_np_np"
    ],
    "discovers": [
        "vbz_interrogative_cl"
    ],
    "eat": [
        "vb_np",
        "vbp_np"
    ],
    "read": [
        "vb_np",
        "vbd_np",
        "vbn_np",
        "vbp_np"
    ],
    "write": [
        "vb_np",
        "vbp_np"
    ],
    "see": [
        "vb_np",
        "vbp_np"
    ],
    "hear": [
        "vb_np",
        "vbp_np"
    ],
    "touch": [
        "vb_np",
        "vbp_np"
    ],
    "hit": [
        "vb_np",
        "vbd_np",
        "vbn_np",
        "vbp_np"
    ],
    "hate": [
        "vb_np",
        "vbp_np"
    ],
    "dislike": [
        "vb_np",
        "vbp_np"
    ],
    "own": [
        "vb_np",
        "vbp_np"
    ],
    "possess": [
        "vb_np",
        "vbp_np"
    ],
    "buy": [
        "vb_np",
        "vbp_np",
        "vb_np_np",
        "vbp_np_np"
    ],
    "send": [
        "vb_np",
        "vbp_np",
        "vb_np_np",
        "vbp_np_np"
    ],
    "order": [
        "vb_np",
        "vbp_np",
        "vb_np_to_inf_cl",
        "vbp_np_to_inf_cl",
        "vb_np_np",
        "vbp_np_np"
    ],
    "offer": [
        "vb_np",
        "vbp_np",
        "vb_np_np",
        "vbp_np_np"
    ],
    "allow": [
        "vb_np",
        "vbp_np"
    ],
    "invite": [
        "vb_np",
        "vbp_np",
        "vb_np_to_inf_cl",
        "vbp_np_to_inf_cl",
        "vb_np_np",
        "vbp_np_np"
    ],
    "advise": [
        "vb_np",
        "vbp_np",
        "vb_np_to_inf_cl",
        "vbp_np_to_inf_cl",
        "vb_np_np",
        "vbp_np_np"
    ],
    "remind": [
        "vb_np",
        "vbp_np",
        "vb_np_to_inf_cl",
        "vbp_np_to_inf_cl",
        "vb_np_np",
        "vbp_np_np"
    ],
    "teach": [
        "vb_np",
        "vbp_np",
        "vb_np_to_inf_cl",
        "vbp_np_to_inf_cl",
        "vb_np_np",
        "vbp_np_np"
    ],
    "prevent": [
        "vb_np",
        "vbp_np"
    ],
    "stop": [
        "vb_np",
        "vbp_np"
    ],
    "avoid": [
        "vb_np",
        "vbp_np"
    ],
    "finish": [
        "vb_np",
        "vbp_np"
    ],
    "start": [
        "vb_np",
        "vbp_np"
    ],
    "continue": [
        "vb_np",
        "vbp_np"
    ],
    "keep": [
        "vb_np",
        "vbp_np"
    ],
    "mind": [
        "vb_np",
        "vbp_np"
    ],
    "miss": [
        "vb_np",
        "vbp_np"
    ],
    "regret": [
        "vb_np",
        "vbp_np"
    ],
    "deny": [
        "vb_np",
        "vbp_np"
    ],
    "confirm": [
        "vb_np",
        "vbp_np"
    ],
    "doubt": [
        "vb_np",
        "vbp_np"
    ],
    "suspect": [
        "vb_np",
        "vbp_np"
    ],
    "ignore": [
        "vb_np",
        "vbp_np"
    ],
    "recognize": [
        "vb_np",
        "vbp_np"
    ],
    "watch": [
        "vb_np",
        "vbp_np"
    ],
    "accept": [
        "vb_np",
        "vbp_np"
    ],
    "achieve": [
        "vb_np",
        "vbp_np"
    ],
    "affect": [
        "vb_np",
        "vbp_np"
    ],
    "blame": [
        "vb_np",
        "vbp_np"
    ],
    "protect": [
        "vb_np",
        "vbp_np"
    ],
    "punch": [
        "vb_np",
        "vbp_np"
    ],
    "raise": [
        "vb_np",
        "vbp_np"
    ],
    "rake": [
        "vb_np",
        "vbp_np"
    ],
    "ram": [
        "vb_np",
        "vbp_np"
    ],
    "rattle": [
        "vb_np",
        "vbp_np"
    ],
    "rearrange": [
        "vb_np",
        "vbp_np"
    ],
    "rebuild": [
        "vb_np",
        "vbp_np"
    ],
    "receive": [
        "vb_np",
        "vbp_np"
    ],
    "recite": [
        "vb_np",
        "vbp_np"
    ],
    "prune": [
        "vb_np",
        "vbp_np"
    ],
    "put": [
        "vb_np",
        "vbd_np",
        "vbn_np",
        "vbp_np"
    ],
    "leave": [
        "vb_np",
        "vbp_np"
    ],
    "meet": [
        "vb_np",
        "vbp_np"
    ],
    "ate": [
        "vbd_np"
    ],
    "wrote": [
        "vbd_np"
    ],
    "saw": [
        "vbd_np"
    ],
    "heard": [
        "vbd_np",
        "vbn_np"
    ],
    "touched": [
        "vbd_np",
        "vbn_np"
    ],
    "hated": [
        "vbd_np",
        "vbn_np"
    ],
    "disliked": [
        "vbd_np",
        "vbn_np"
    ],
    "owned": [
        "vbd_np",
        "vbn_np"
    ],
    "possessed": [
        "vbd_np",
        "vbn_np"
    ],
    "bought": [
        "vbd_np",
        "vbn_np",
        "vbd_np_np",
        "vbn_np_np"
    ],
    "sent": [
        "vbd_np",
        "vbn_np",
        "vbd_np_np",
        "vbn_np_np"
    ],
    "ordered": [
        "vbd_np",
        "vbn_np",
        "vbd_np_to_inf_cl",
        "vbn_np_to_inf_cl",
        "vbd_np_np",
        "vbn_np_np"
    ],
    "offered": [
        "vbd_np",
        "vbn_np",
        "vbd_np_np",
        "vbn_np_np"
    ],
    "allowed": [
        "vbd_np",
        "vbn_np"
    ],
    "invited": [
        "vbd_np",
        "vbn_np",
        "vbd_np_to_inf_cl",
        "vbn_np_to_inf_cl",
        "vbd_np_np",
        "vbn_np_np"
    ],
    "advised": [
        "vbd_np",
        "vbn_np",
        "vbd_np_to_inf_cl",
        "vbn_np_to_inf_cl",
        "vbd_np_np",
        "vbn_np_np"
    ],
    "reminded": [
        "vbd_np",
        "vbn_np",
        "vbd_np_to_inf_cl",
        "vbn_np_to_inf_cl",
        "vbd_np_np",
        "vbn_np_np"
    ],
    "teached": [
        "vbd_np",
        "vbn_np",
        "vbd_np_to_inf_cl",
        "vbn_np_to_inf_cl",
        "vbd_np_np",
        "vbn_np_np"
    ],
    "prevented": [
        "vbd_np",
        "vbn_np"
    ],
    "stopped": [
        "vbd_np",
        "vbn_np"
    ],
    "avoided": [
        "vbd_np",
        "vbn_np"
    ],
    "finished": [
        "vbd_np",
        "vbn_np"
    ],
    "started": [
        "vbd_np",
        "vbn_np"
    ],
    "continued": [
        "vbd_np",
        "vbn_np"
    ],
    "kept": [
        "vbd_np",
        "vbn_np"
    ],
    "minded": [
        "vbd_np",
        "vbn_np"
    ],
    "missed": [
        "vbd_np",
        "vbn_np"
    ],
    "regretted": [
        "vbd_np",
        "vbn_np"
    ],
    "wished": [
        "vbd_np",
        "vbn_np"
    ],
    "denied": [
        "vbd_np",
        "vbn_np"
    ],
    "confirmed": [
        "vbd_np",
        "vbn_np"
    ],
    "doubted": [
        "vbd_np",
        "vbn_np"
    ],
    "suspected": [
        "vbd_np",
        "vbn_np"
    ],
    "ignored": [
        "vbd_np",
        "vbn_np"
    ],
    "recognized": [
        "vbd_np",
        "vbn_np"
    ],
    "watched": [
        "vbd_np",
        "vbn_np"
    ],
    "accepted": [
        "vbd_np",
        "vbn_np"
    ],
    "achieved": [
        "vbd_np",
        "vbn_np"
    ],
    "affected": [
        "vbd_np",
        "vbn_np"
    ],
    "blamed": [
        "vbd_np",
        "vbn_np"
    ],
    "protected": [
        "vbd_np",
        "vbn_np"
    ],
    "punched": [
        "vbd_np",
        "vbn_np"
    ],
    "raised": [
        "vbd_np",
        "vbn_np"
    ],
    "raked": [
        "vbd_np",
        "vbn_np"
    ],
    "ramed": [
        "vbd_np",
        "vbn_np"
    ],
    "rattled": [
        "vbd_np",
        "vbn_np"
    ],
    "rearranged": [
        "vbd_np",
        "vbn_np"
    ],
    "rebuilded": [
        "vbd_np",
        "vbn_np"
    ],
    "received": [
        "vbd_np",
        "vbn_np"
    ],
    "recited": [
        "vbd_np",
        "vbn_np"
    ],
    "pruned": [
        "vbd_np",
        "vbn_np"
    ],
    "leaved": [
        "vbd_np",
        "vbn_np"
    ],
    "met": [
        "vbd_np",
        "vbn_np"
    ],
    "eaten": [
        "vbn_np"
    ],
    "written": [
        "vbn_np"
    ],
    "seen": [
        "vbn_np"
    ],
    "eating": [
        "vbg_np"
    ],
    "reading": [
        "vbg_np"
    ],
    "writing": [
        "vbg_np"
    ],
    "seeing": [
        "vbg_np"
    ],
    "hearing": [
        "vbg_np"
    ],
    "touching": [
        "vbg_np"
    ],
    "hitting": [
        "vbg_np"
    ],
    "hating": [
        "vbg_np"
    ],
    "disliking": [
        "vbg_np"
    ],
    "owning": [
        "vbg_np"
    ],
    "possessing": [
        "vbg_np"
    ],
    "buying": [
        "vbg_np",
        "vbg_np_np"
    ],
    "sending": [
        "vbg_np",
        "vbg_np_np"
    ],
    "ordering": [
        "vbg_np",
        "vbg_np_to_inf_cl",
        "vbg_np_np"
    ],
    "offering": [
        "vbg_np",
        "vbg_np_np"
    ],
    "allowing": [
        "vbg_np"
    ],
    "inviting": [
        "vbg_np",
        "vbg_np_to_inf_cl",
        "vbg_np_np"
    ],
    "advising": [
        "vbg_np",
        "vbg_np_to_inf_cl",
        "vbg_np_np"
    ],
    "reminding": [
        "vbg_np",
        "vbg_np_to_inf_cl",
        "vbg_np_np"
    ],
    "teaching": [
        "vbg_np",
        "vbg_np_to_inf_cl",
        "vbg_np_np"
    ],
    "preventing": [
        "vbg_np"
    ],
    "stopping": [
        "vbg_np"
    ],
    "avoiding": [
        "vbg_np"
    ],
    "finishing": [
        "vbg_np"
    ],
    "starting": [
        "vbg_np"
    ],
    "continuing": [
        "vbg_np"
    ],
    "keeping": [
        "vbg_np"
    ],
    "minding": [
        "vbg_np"
    ],
    "missing": [
        "vbg_np"
    ],
    "regretting": [
        "vbg_np"
    ],
    "wishing": [
        "vbg_np"
    ],
    "denying": [
        "vbg_np"
    ],
    "confirming": [
        "vbg_np"
    ],
    "doubting": [
        "vbg_np"
    ],
    "suspecting": [
        "vbg_np"
    ],
    "ignoring": [
        "vbg_np"
    ],
    "recognizing": [
        "vbg_np"
    ],
    "watching": [
        "vbg_np"
    ],
    "accepting": [
        "vbg_np"
    ],
    "achieving": [
        "vbg_np"
    ],
    "affecting": [
        "vbg_np"
    ],
    "blaming": [
        "vbg_np"
    ],
    "protecting": [
        "vbg_np"
    ],
    "punching": [
        "vbg_np"
    ],
    "raising": [
        "vbg_np"
    ],
    "raking": [
        "vbg_np"
    ],
    "raming": [
        "vbg_np"
    ],
    "rattling": [
        "vbg_np"
    ],
    "rearranging": [
        "vbg_np"
    ],
    "rebuilding": [
        "vbg_np"
    ],
    "receiving": [
        "vbg_np"
    ],
    "reciting": [
        "vbg_np"
    ],
    "pruning": [
        "vbg_np"
    ],
    "putting": [
        "vbg_np"
    ],
    "leaving": [
        "vbg_np"
    ],
    "meeting": [
        "vbg_np"
    ],
    "eats": [
        "vbz_np"
    ],
    "reads": [
        "vbz_np"
    ],
    "writes": [
        "vbz_np"
    ],
    "sees": [
        "vbz_np"
    ],
    "hears": [
        "vbz_np"
    ],
    "touches": [
        "vbz_np"
    ],
    "hits": [
        "vbz_np"
    ],
    "hates": [
        "vbz_np"
    ],
    "dislikes": [
        "vbz_np"
    ],
    "owns": [
        "vbz_np"
    ],
    "possesses": [
        "vbz_np"
    ],
    "buys": [
        "vbz_np",
        "vbz_np_np"
    ],
    "sends": [
        "vbz_np",
        "vbz_np_np"
    ],
    "orders": [
        "vbz_np",
        "vbz_np_to_inf_cl",
        "vbz_np_np"
    ],
    "offers": [
        "vbz_np",
        "vbz_np_np"
    ],
    "allows": [
        "vbz_np"
    ],
    "invites": [
        "vbz_np",
        "vbz_np_to_inf_cl",
        "vbz_np_np"
    ],
    "advises": [
        "vbz_np",
        "vbz_np_to_inf_cl",
        "vbz_np_np"
    ],
    "reminds": [
        "vbz_np",
        "vbz_np_to_inf_cl",
        "vbz_np_np"
    ],
    "teaches": [
        "vbz_np",
        "vbz_np_to_inf_cl",
        "vbz_np_np"
    ],
    "prevents": [
        "vbz_np"
    ],
    "stops": [
        "vbz_np"
    ],
    "avoids": [
        "vbz_np"
    ],
    "finishes": [
        "vbz_np"
    ],
    "starts": [
        "vbz_np"
    ],
    "continues": [
        "vbz_np"
    ],
    "keeps": [
        "vbz_np"
    ],
    "minds": [
        "vbz_np"
    ],
    "misses": [
        "vbz_np"
    ],
    "regrets": [
        "vbz_np"
    ],
    "denies": [
        "vbz_np"
    ],
    "confirms": [
        "vbz_np"
    ],
    "doubts": [
        "vbz_np"
    ],
    "suspects": [
        "vbz_np"
    ],
    "ignores": [
        "vbz_np"
    ],
    "recognizes": [
        "vbz_np"
    ],
    "watches": [
        "vbz_np"
    ],
    "accepts": [
        "vbz_np"
    ],
    "achieves": [
        "vbz_np"
    ],
    "affects": [
        "vbz_np"
    ],
    "blames": [
        "vbz_np"
    ],
    "protects": [
        "vbz_np"
    ],
    "punches": [
        "vbz_np"
    ],
    "raises": [
        "vbz_np"
    ],
    "rakes": [
        "vbz_np"
    ],
    "rams": [
        "vbz_np"
    ],
    "rattles": [
        "vbz_np"
    ],
    "rearranges": [
        "vbz_np"
    ],
    "rebuilds": [
        "vbz_np"
    ],
    "receives": [
        "vbz_np"
    ],
    "recites": [
        "vbz_np"
    ],
    "prunes": [
        "vbz_np"
    ],
    "puts": [
        "vbz_np"
    ],
    "leaves": [
        "vbz_np"
    ],
    "meets": [
        "vbz_np"
    ],
    "make": [
        "vb_np_ap",
        "vbp_np_ap",
        "vb_np_bare_inf_cl",
        "vbp_np_bare_inf_cl"
    ],
    "made": [
        "vbd_np_ap",
        "vbn_np_ap",
        "vbd_np_bare_inf_cl",
        "vbn_np_bare_inf_cl"
    ],
    "making": [
        "vbg_np_ap",
        "vbg_np_bare_inf_cl"
    ],
    "makes": [
        "vbz_np_ap",
        "vbz_np_bare_inf_cl"
    ],
    "let": [
        "vb_np_bare_inf_cl",
        "vbd_np_bare_inf_cl",
        "vbn_np_bare_inf_cl",
        "vbp_np_bare_inf_cl"
    ],
    "letting": [
        "vbg_np_bare_inf_cl"
    ],
    "lets": [
        "vbz_np_bare_inf_cl"
    ],
    "give": [
        "vb_np_np",
        "vbp_np_np"
    ],
    "bring": [
        "vb_np_np",
        "vbp_np_np"
    ],
    "lend": [
        "vb_np_np",
        "vbp_np_np"
    ],
    "pass": [
        "vb_np_np",
        "vbp_np_np"
    ],
    "hand": [
        "vb_np_np",
        "vbp_np_np"
    ],
    "sell": [
        "vb_np_np",
        "vbp_np_np"
    ],
    "pay": [
        "vb_np_np",
        "vbp_np_np"
    ],
    "gave": [
        "vbd_np_np"
    ],
    "brought": [
        "vbd_np_np",
        "vbn_np_np"
    ],
    "lent": [
        "vbd_np_np",
        "vbn_np_np"
    ],
    "passed": [
        "vbd_np_np",
        "vbn_np_np"
    ],
    "handed": [
        "vbd_np_np",
        "vbn_np_np"
    ],
    "sold": [
        "vbd_np_np",
        "vbn_np_np"
    ],
    "paid": [
        "vbd_np_np",
        "vbn_np_np"
    ],
    "given": [
        "vbn_np_np"
    ],
    "giving": [
        "vbg_np_np"
    ],
    "bringing": [
        "vbg_np_np"
    ],
    "lending": [
        "vbg_np_np"
    ],
    "passing": [
        "vbg_np_np"
    ],
    "handing": [
        "vbg_np_np"
    ],
    "selling": [
        "vbg_np_np"
    ],
    "paying": [
        "vbg_np_np"
    ],
    "gives": [
        "vbz_np_np"
    ],
    "brings": [
        "vbz_np_np"
    ],
    "lends": [
        "vbz_np_np"
    ],
    "passes": [
        "vbz_np_np"
    ],
    "hands": [
        "vbz_np_np"
    ],
    "sells": [
        "vbz_np_np"
    ],
    "pays": [
        "vbz_np_np"
    ],
    "with": [
        "instrumental_preposition",
        "comitative_preposition",
        "preposition"
    ],
    "using": [
        "instrumental_preposition",
        "preposition"
    ],
    "in": [
        "spatial_preposition",
        "temporal_point_preposition",
        "preposition"
    ],
    "on": [
        "spatial_preposition",
        "temporal_point_preposition",
        "preposition"
    ],
    "at": [
        "spatial_preposition",
        "temporal_point_preposition",
        "preposition"
    ],
    "over": [
        "spatial_preposition",
        "preposition"
    ],
    "under": [
        "spatial_preposition",
        "preposition"
    ],
    "underneath": [
        "spatial_preposition",
        "preposition"
    ],
    "between": [
        "spatial_preposition",
        "preposition"
    ],
    "among": [
        "spatial_preposition",
        "preposition"
    ],
    "within": [
        "spatial_preposition",
        "temporal_duration_preposition",
        "preposition"
    ],
    "above": [
        "spatial_preposition",
        "preposition"
    ],
    "below": [
        "spatial_preposition",
        "preposition"
    ],
    "beside": [
        "spatial_preposition",
        "preposition"
    ],
    "from": [
        "source_preposition",
        "preposition"
    ],
    "off": [
        "source_preposition",
        "goal_preposition",
        "preposition"
    ],
    "out": [
        "source_preposition",
        "preposition"
    ],
    "toward": [
        "goal_preposition",
        "preposition"
    ],
    "towards": [
        "goal_preposition",
        "preposition"
    ],
    "into": [
        "goal_preposition",
        "preposition"
    ],
    "onto": [
        "goal_preposition",
        "preposition"
    ],
    "upon": [
        "goal_preposition",
        "preposition"
    ],
    "up": [
        "goal_preposition",
        "preposition"
    ],
    "down": [
        "goal_preposition",
        "preposition"
    ],
    "inside": [
        "goal_preposition",
        "preposition"
    ],
    "outside": [
        "goal_preposition",
        "preposition"
    ],
    "around": [
        "goal_preposition",
        "preposition"
    ],
    "aboard": [
        "goal_preposition",
        "preposition"
    ],
    "across": [
        "goal_preposition",
        "preposition"
    ],
    "along": [
        "goal_preposition",
        "preposition"
    ],
    "for": [
        "temporal_duration_preposition",
        "preposition"
    ],
    "since": [
        "temporal_duration_preposition",
        "preposition"
    ],
    "until": [
        "temporal_duration_preposition",
        "preposition"
    ],
    "before": [
        "temporal_duration_preposition",
        "preposition"
    ],
    "after": [
        "temporal_duration_preposition",
        "preposition"
    ],
    "by": [
        "temporal_duration_preposition",
        "preposition"
    ],
    "during": [
        "temporal_duration_preposition",
        "preposition"
    ]
}